{
  "scorecard": [
    {
      "inningsid": 1,
      "batsman": [
        {
          "id": 13940,
          "balls": 36,
          "runs": 55,
          "fours": 6,
          "sixes": 3,
          "strkrate": "152.78",
          "name": "Yashasvi Jaiswal",
          "nickname": "Yashasvi Jaiswal",
          "iscaptain": false,
          "iskeeper": false,
          "outdec": "b Kagiso Rabada",
          "videotype": "",
          "videourl": "",
          "videoid": 0,
          "planid": 0,
          "imageid": 0,
          "premiumvideourl": "",
          "iscbplusfree": false,
          "ispremiumfree": false,
          "inmatchchange": "",
          "isoverseas": false,
          "playingxichange": ""
        },
        {
          "id": 51791,
          "balls": 18,
          "runs": 31,
          "fours": 5,
          "sixes": 1,
          "strkrate": "172.22",
          "name": "Vaibhav Sooryavanshi",
          "nickname": "Vaibhav Sooryavanshi",
          "iscaptain": false,
          "iskeeper": false,
          "outdec": "c Glenn Phillips b Rashid Khan",
          "videotype": "",
          "videourl": "",
          "videoid": 0,
          "planid": 0,
          "imageid": 0,
          "premiumvideourl": "",
          "iscbplusfree": false,
          "ispremiumfree": false,
          "inmatchchange": "",
          "isoverseas": false,
          "playingxichange": ""
        },
        {
          "id": 14691,
          "balls": 42,
          "runs": 75,
          "fours": 5,
          "sixes": 5,
          "strkrate": "178.57",
          "name": "Dhruv Jurel",
          "nickname": "Dhruv Jurel",
          "iscaptain": false,
          "iskeeper": true,
          "outdec": "c Jos Buttler b Mohammed Siraj",
          "videotype": "",
          "videourl": "",
          "videoid": 0,
          "planid": 0,
          "imageid": 0,
          "premiumvideourl": "",
          "iscbplusfree": false,
          "ispremiumfree": false,
          "inmatchchange": "",
          "isoverseas": false,
          "playingxichange": ""
        },
        {
          "id": 12305,
          "balls": 4,
          "runs": 8,
          "fours": 0,
          "sixes": 1,
          "strkrate": "200",
          "name": "Riyan Parag",
          "nickname": "Riyan Parag",
          "iscaptain": true,
          "iskeeper": false,
          "outdec": "c Kumar Kushagra b Prasidh Krishna",
          "videotype": "",
          "videourl": "",
          "videoid": 0,
          "planid": 0,
          "imageid": 0,
          "premiumvideourl": "",
          "iscbplusfree": false,
          "ispremiumfree": false,
          "inmatchchange": "",
          "isoverseas": false,
          "playingxichange": ""
        },
        {
          "id": 9789,
          "balls": 8,
          "runs": 18,
          "fours": 1,
          "sixes": 2,
          "strkrate": "225",
          "name": "Shimron Hetmyer",
          "nickname": "Shimron Hetmyer",
          "iscaptain": false,
          "iskeeper": false,
          "outdec": "c Mohammed Siraj b Ashok Sharma",
          "videotype": "",
          "videourl": "",
          "videoid": 0,
          "planid": 0,
          "imageid": 0,
          "premiumvideourl": "",
          "iscbplusfree": false,
          "ispremiumfree": false,
          "inmatchchange": "",
          "isoverseas": true,
          "playingxichange": ""
        },
        {
          "id": 14798,
          "balls": 3,
          "runs": 1,
          "fours": 0,
          "sixes": 0,
          "strkrate": "33.33",
          "name": "Donovan Ferreira",
          "nickname": "Donovan Ferreira",
          "iscaptain": false,
          "iskeeper": false,
          "outdec": "c Glenn Phillips b Kagiso Rabada",
          "videotype": "",
          "videourl": "",
          "videoid": 0,
          "planid": 0,
          "imageid": 0,
          "premiumvideourl": "",
          "iscbplusfree": false,
          "ispremiumfree": false,
          "inmatchchange": "MOUT",
          "isoverseas": true,
          "playingxichange": "IN"
        },
        {
          "id": 587,
          "balls": 7,
          "runs": 7,
          "fours": 1,
          "sixes": 0,
          "strkrate": "100",
          "name": "Ravindra Jadeja",
          "nickname": "Ravindra Jadeja",
          "iscaptain": false,
          "iskeeper": false,
          "outdec": "not out",
          "videotype": "",
          "videourl": "",
          "videoid": 0,
          "planid": 0,
          "imageid": 0,
          "premiumvideourl": "",
          "iscbplusfree": false,
          "ispremiumfree": false,
          "inmatchchange": "",
          "isoverseas": false,
          "playingxichange": ""
        },
        {
          "id": 11540,
          "balls": 2,
          "runs": 1,
          "fours": 0,
          "sixes": 0,
          "strkrate": "50",
          "name": "Jofra Archer",
          "nickname": "Jofra Archer",
          "iscaptain": false,
          "iskeeper": false,
          "outdec": "not out",
          "videotype": "",
          "videourl": "",
          "videoid": 0,
          "planid": 0,
          "imageid": 0,
          "premiumvideourl": "",
          "iscbplusfree": false,
          "ispremiumfree": false,
          "inmatchchange": "",
          "isoverseas": true,
          "playingxichange": ""
        },
        {
          "id": 13630,
          "balls": 0,
          "runs": 0,
          "fours": 0,
          "sixes": 0,
          "strkrate": "0",
          "name": "Nandre Burger",
          "nickname": "Nandre Burger",
          "iscaptain": false,
          "iskeeper": false,
          "outdec": "",
          "videotype": "",
          "videourl": "",
          "videoid": 0,
          "planid": 0,
          "imageid": 0,
          "premiumvideourl": "",
          "iscbplusfree": false,
          "ispremiumfree": false,
          "inmatchchange": "",
          "isoverseas": true,
          "playingxichange": ""
        },
        {
          "id": 11307,
          "balls": 0,
          "runs": 0,
          "fours": 0,
          "sixes": 0,
          "strkrate": "0",
          "name": "Tushar Deshpande",
          "nickname": "Tushar Deshpande",
          "iscaptain": false,
          "iskeeper": false,
          "outdec": "",
          "videotype": "",
          "videourl": "",
          "videoid": 0,
          "planid": 0,
          "imageid": 0,
          "premiumvideourl": "",
          "iscbplusfree": false,
          "ispremiumfree": false,
          "inmatchchange": "",
          "isoverseas": false,
          "playingxichange": "IN"
        },
        {
          "id": 8356,
          "balls": 0,
          "runs": 0,
          "fours": 0,
          "sixes": 0,
          "strkrate": "0",
          "name": "Sandeep Sharma",
          "nickname": "Sandeep Sharma",
          "iscaptain": false,
          "iskeeper": false,
          "outdec": "",
          "videotype": "",
          "videourl": "",
          "videoid": 0,
          "planid": 0,
          "imageid": 0,
          "premiumvideourl": "",
          "iscbplusfree": false,
          "ispremiumfree": false,
          "inmatchchange": "",
          "isoverseas": false,
          "playingxichange": ""
        },
        {
          "id": 14659,
          "balls": 0,
          "runs": 0,
          "fours": 0,
          "sixes": 0,
          "strkrate": "0",
          "name": "Ravi Bishnoi",
          "nickname": "Ravi Bishnoi",
          "iscaptain": false,
          "iskeeper": false,
          "outdec": "",
          "videotype": "",
          "videourl": "",
          "videoid": 0,
          "planid": 0,
          "imageid": 0,
          "premiumvideourl": "",
          "iscbplusfree": false,
          "ispremiumfree": false,
          "inmatchchange": "MIN",
          "isoverseas": false,
          "playingxichange": "OUT"
        }
      ],
      "bowler": [
        {
          "id": 10808,
          "overs": "4",
          "maidens": 0,
          "wickets": 1,
          "runs": 48,
          "economy": "12",
          "name": "Mohammed Siraj",
          "nickname": "Mohammed Siraj",
          "iscaptain": false,
          "iskeeper": false,
          "videotype": "",
          "videourl": "",
          "videoid": 0,
          "dots": 0,
          "balls": 40,
          "rpb": 1.2,
          "planid": 0,
          "imageid": 0,
          "premiumvideourl": "",
          "ispremiumfree": false,
          "inmatchchange": "",
          "isoverseas": false,
          "playingxichange": ""
        },
        {
          "id": 9585,
          "overs": "4",
          "maidens": 0,
          "wickets": 2,
          "runs": 42,
          "economy": "10.5",
          "name": "Kagiso Rabada",
          "nickname": "Kagiso Rabada",
          "iscaptain": false,
          "iskeeper": false,
          "videotype": "",
          "videourl": "",
          "videoid": 0,
          "dots": 0,
          "balls": 40,
          "rpb": 1.05,
          "planid": 0,
          "imageid": 0,
          "premiumvideourl": "",
          "ispremiumfree": false,
          "inmatchchange": "",
          "isoverseas": true,
          "playingxichange": ""
        },
        {
          "id": 24261,
          "overs": "4",
          "maidens": 0,
          "wickets": 1,
          "runs": 37,
          "economy": "9.2",
          "name": "Ashok Sharma",
          "nickname": "Ashok Sharma",
          "iscaptain": false,
          "iskeeper": false,
          "videotype": "",
          "videourl": "",
          "videoid": 0,
          "dots": 0,
          "balls": 40,
          "rpb": 0.93,
          "planid": 0,
          "imageid": 0,
          "premiumvideourl": "",
          "ispremiumfree": false,
          "inmatchchange": "",
          "isoverseas": false,
          "playingxichange": ""
        },
        {
          "id": 10551,
          "overs": "4",
          "maidens": 0,
          "wickets": 1,
          "runs": 43,
          "economy": "10.8",
          "name": "Prasidh Krishna",
          "nickname": "Prasidh Krishna",
          "iscaptain": false,
          "iskeeper": false,
          "videotype": "",
          "videourl": "",
          "videoid": 0,
          "dots": 0,
          "balls": 40,
          "rpb": 1.07,
          "planid": 0,
          "imageid": 0,
          "premiumvideourl": "",
          "ispremiumfree": false,
          "inmatchchange": "MOUT",
          "isoverseas": false,
          "playingxichange": ""
        },
        {
          "id": 10738,
          "overs": "4",
          "maidens": 0,
          "wickets": 1,
          "runs": 39,
          "economy": "9.8",
          "name": "Rashid Khan",
          "nickname": "Rashid Khan",
          "iscaptain": true,
          "iskeeper": false,
          "videotype": "",
          "videourl": "",
          "videoid": 0,
          "dots": 0,
          "balls": 40,
          "rpb": 0.97,
          "planid": 0,
          "imageid": 0,
          "premiumvideourl": "",
          "ispremiumfree": false,
          "inmatchchange": "",
          "isoverseas": true,
          "playingxichange": ""
        }
      ],
      "fow": {
        "fow": [
          {
            "batsmanid": 51791,
            "batsmanname": "Vaibhav Sooryavanshi",
            "overnbr": 6.2,
            "runs": 70,
            "ballnbr": 38
          },
          {
            "batsmanid": 13940,
            "batsmanname": "Yashasvi Jaiswal",
            "overnbr": 12.3,
            "runs": 126,
            "ballnbr": 75
          },
          {
            "batsmanid": 12305,
            "batsmanname": "Riyan Parag",
            "overnbr": 13.2,
            "runs": 135,
            "ballnbr": 80
          },
          {
            "batsmanid": 9789,
            "batsmanname": "Shimron Hetmyer",
            "overnbr": 15.3,
            "runs": 165,
            "ballnbr": 93
          },
          {
            "batsmanid": 14798,
            "batsmanname": "Donovan Ferreira",
            "overnbr": 16.1,
            "runs": 166,
            "ballnbr": 97
          },
          {
            "batsmanid": 14691,
            "batsmanname": "Dhruv Jurel",
            "overnbr": 19.3,
            "runs": 205,
            "ballnbr": 117
          }
        ]
      },
      "extras": {
        "legbyes": 1,
        "byes": 0,
        "wides": 13,
        "noballs": 0,
        "penalty": 0,
        "total": 14
      },
      "score": 210,
      "wickets": 6,
      "overs": 20.0,
      "runrate": 10.5,
      "batteamname": "Rajasthan Royals",
      "batteamsname": "RR",
      "isdeclared": false,
      "isfollowon": false,
      "ballnbr": 120,
      "rpb": 1.75,
      "partnership": {
        "partnership": [
          {
            "id": 0,
            "bat1id": 13940,
            "bat1name": "Yashasvi Jaiswal",
            "bat1runs": 36,
            "bat1fours": 3,
            "bat1sixes": 3,
            "bat2id": 51791,
            "bat2name": "Vaibhav Sooryavanshi",
            "bat2runs": 31,
            "bat2fours": 5,
            "bat2sixes": 1,
            "totalruns": 70,
            "totalballs": 38,
            "bat1balls": 20,
            "bat2balls": 18,
            "teamname": "",
            "teamid": 0,
            "bat1ones": 4,
            "bat1twos": 1,
            "bat1threes": 0,
            "bat1fives": 0,
            "bat1boundaries": 3,
            "bat1sixers": 3,
            "bat2ones": 5,
            "bat2twos": 0,
            "bat2threes": 0,
            "bat2fives": 0,
            "bat2boundaries": 5,
            "bat2sixers": 1
          },
          {
            "id": 0,
            "bat1id": 13940,
            "bat1name": "Yashasvi Jaiswal",
            "bat1runs": 19,
            "bat1fours": 3,
            "bat1sixes": 0,
            "bat2id": 14691,
            "bat2name": "Dhruv Jurel",
            "bat2runs": 31,
            "bat2fours": 4,
            "bat2sixes": 1,
            "totalruns": 56,
            "totalballs": 37,
            "bat1balls": 16,
            "bat2balls": 21,
            "teamname": "",
            "teamid": 0,
            "bat1ones": 5,
            "bat1twos": 1,
            "bat1threes": 0,
            "bat1fives": 0,
            "bat1boundaries": 3,
            "bat1sixers": 0,
            "bat2ones": 7,
            "bat2twos": 1,
            "bat2threes": 0,
            "bat2fives": 0,
            "bat2boundaries": 4,
            "bat2sixers": 1
          },
          {
            "id": 0,
            "bat1id": 12305,
            "bat1name": "Riyan Parag",
            "bat1runs": 8,
            "bat1fours": 0,
            "bat1sixes": 1,
            "bat2id": 14691,
            "bat2name": "Dhruv Jurel",
            "bat2runs": 1,
            "bat2fours": 0,
            "bat2sixes": 0,
            "totalruns": 9,
            "totalballs": 5,
            "bat1balls": 4,
            "bat2balls": 1,
            "teamname": "",
            "teamid": 0,
            "bat1ones": 0,
            "bat1twos": 1,
            "bat1threes": 0,
            "bat1fives": 0,
            "bat1boundaries": 0,
            "bat1sixers": 1,
            "bat2ones": 1,
            "bat2twos": 0,
            "bat2threes": 0,
            "bat2fives": 0,
            "bat2boundaries": 0,
            "bat2sixers": 0
          },
          {
            "id": 0,
            "bat1id": 9789,
            "bat1name": "Shimron Hetmyer",
            "bat1runs": 18,
            "bat1fours": 1,
            "bat1sixes": 2,
            "bat2id": 14691,
            "bat2name": "Dhruv Jurel",
            "bat2runs": 10,
            "bat2fours": 0,
            "bat2sixes": 1,
            "totalruns": 30,
            "totalballs": 13,
            "bat1balls": 8,
            "bat2balls": 5,
            "teamname": "",
            "teamid": 0,
            "bat1ones": 2,
            "bat1twos": 0,
            "bat1threes": 0,
            "bat1fives": 0,
            "bat1boundaries": 1,
            "bat1sixers": 2,
            "bat2ones": 4,
            "bat2twos": 0,
            "bat2threes": 0,
            "bat2fives": 0,
            "bat2boundaries": 0,
            "bat2sixers": 1
          },
          {
            "id": 0,
            "bat1id": 14798,
            "bat1name": "Donovan Ferreira",
            "bat1runs": 1,
            "bat1fours": 0,
            "bat1sixes": 0,
            "bat2id": 14691,
            "bat2name": "Dhruv Jurel",
            "bat2runs": 0,
            "bat2fours": 0,
            "bat2sixes": 0,
            "totalruns": 1,
            "totalballs": 4,
            "bat1balls": 3,
            "bat2balls": 1,
            "teamname": "",
            "teamid": 0,
            "bat1ones": 1,
            "bat1twos": 0,
            "bat1threes": 0,
            "bat1fives": 0,
            "bat1boundaries": 0,
            "bat1sixers": 0,
            "bat2ones": 0,
            "bat2twos": 0,
            "bat2threes": 0,
            "bat2fives": 0,
            "bat2boundaries": 0,
            "bat2sixers": 0
          },
          {
            "id": 0,
            "bat1id": 587,
            "bat1name": "Ravindra Jadeja",
            "bat1runs": 3,
            "bat1fours": 0,
            "bat1sixes": 0,
            "bat2id": 14691,
            "bat2name": "Dhruv Jurel",
            "bat2runs": 33,
            "bat2fours": 1,
            "bat2sixes": 3,
            "totalruns": 39,
            "totalballs": 20,
            "bat1balls": 6,
            "bat2balls": 14,
            "teamname": "",
            "teamid": 0,
            "bat1ones": 3,
            "bat1twos": 0,
            "bat1threes": 0,
            "bat1fives": 0,
            "bat1boundaries": 0,
            "bat1sixers": 0,
            "bat2ones": 5,
            "bat2twos": 3,
            "bat2threes": 0,
            "bat2fives": 0,
            "bat2boundaries": 1,
            "bat2sixers": 3
          },
          {
            "id": 0,
            "bat1id": 587,
            "bat1name": "Ravindra Jadeja",
            "bat1runs": 4,
            "bat1fours": 1,
            "bat1sixes": 0,
            "bat2id": 11540,
            "bat2name": "Jofra Archer",
            "bat2runs": 1,
            "bat2fours": 0,
            "bat2sixes": 0,
            "totalruns": 5,
            "totalballs": 3,
            "bat1balls": 1,
            "bat2balls": 2,
            "teamname": "",
            "teamid": 0,
            "bat1ones": 0,
            "bat1twos": 0,
            "bat1threes": 0,
            "bat1fives": 0,
            "bat1boundaries": 1,
            "bat1sixers": 0,
            "bat2ones": 1,
            "bat2twos": 0,
            "bat2threes": 0,
            "bat2fives": 0,
            "bat2boundaries": 0,
            "bat2sixers": 0
          }
        ]
      }
    },
    {
      "inningsid": 2,
      "batsman": [
        {
          "id": 13866,
          "balls": 44,
          "runs": 73,
          "fours": 9,
          "sixes": 3,
          "strkrate": "165.91",
          "name": "Sai Sudharsan",
          "nickname": "Sai Sudharsan",
          "iscaptain": false,
          "iskeeper": false,
          "outdec": "c Tushar Deshpande b Ravi Bishnoi",
          "videotype": "",
          "videourl": "",
          "videoid": 0,
          "planid": 0,
          "imageid": 0,
          "premiumvideourl": "",
          "iscbplusfree": false,
          "ispremiumfree": false,
          "inmatchchange": "",
          "isoverseas": false,
          "playingxichange": ""
        },
        {
          "id": 15779,
          "balls": 14,
          "runs": 18,
          "fours": 3,
          "sixes": 0,
          "strkrate": "128.57",
          "name": "Kumar Kushagra",
          "nickname": "Kumar Kushagra",
          "iscaptain": false,
          "iskeeper": false,
          "outdec": "c Shimron Hetmyer b Riyan Parag",
          "videotype": "",
          "videourl": "",
          "videoid": 0,
          "planid": 0,
          "imageid": 0,
          "premiumvideourl": "",
          "iscbplusfree": false,
          "ispremiumfree": false,
          "inmatchchange": "",
          "isoverseas": false,
          "playingxichange": "IN"
        },
        {
          "id": 2258,
          "balls": 14,
          "runs": 26,
          "fours": 5,
          "sixes": 0,
          "strkrate": "185.71",
          "name": "Jos Buttler",
          "nickname": "Jos Buttler",
          "iscaptain": false,
          "iskeeper": true,
          "outdec": "c Sandeep Sharma b Nandre Burger",
          "videotype": "",
          "videourl": "",
          "videoid": 0,
          "planid": 0,
          "imageid": 0,
          "premiumvideourl": "",
          "iscbplusfree": false,
          "ispremiumfree": false,
          "inmatchchange": "",
          "isoverseas": true,
          "playingxichange": ""
        },
        {
          "id": 10693,
          "balls": 4,
          "runs": 3,
          "fours": 0,
          "sixes": 0,
          "strkrate": "75",
          "name": "Glenn Phillips",
          "nickname": "Glenn Phillips",
          "iscaptain": false,
          "iskeeper": false,
          "outdec": "c Jofra Archer b Ravi Bishnoi",
          "videotype": "",
          "videourl": "",
          "videoid": 0,
          "planid": 0,
          "imageid": 0,
          "premiumvideourl": "",
          "iscbplusfree": false,
          "ispremiumfree": false,
          "inmatchchange": "",
          "isoverseas": true,
          "playingxichange": ""
        },
        {
          "id": 10945,
          "balls": 2,
          "runs": 4,
          "fours": 1,
          "sixes": 0,
          "strkrate": "200",
          "name": "Washington Sundar",
          "nickname": "Washington Sundar",
          "iscaptain": false,
          "iskeeper": false,
          "outdec": "c Ravindra Jadeja b Ravi Bishnoi",
          "videotype": "",
          "videourl": "",
          "videoid": 0,
          "planid": 0,
          "imageid": 0,
          "premiumvideourl": "",
          "iscbplusfree": false,
          "ispremiumfree": false,
          "inmatchchange": "",
          "isoverseas": false,
          "playingxichange": ""
        },
        {
          "id": 9693,
          "balls": 6,
          "runs": 12,
          "fours": 1,
          "sixes": 1,
          "strkrate": "200",
          "name": "Rahul Tewatia",
          "nickname": "Rahul Tewatia",
          "iscaptain": false,
          "iskeeper": false,
          "outdec": "c Dhruv Jurel b Ravi Bishnoi",
          "videotype": "",
          "videourl": "",
          "videoid": 0,
          "planid": 0,
          "imageid": 0,
          "premiumvideourl": "",
          "iscbplusfree": false,
          "ispremiumfree": false,
          "inmatchchange": "",
          "isoverseas": false,
          "playingxichange": ""
        },
        {
          "id": 10226,
          "balls": 4,
          "runs": 11,
          "fours": 1,
          "sixes": 1,
          "strkrate": "275",
          "name": "Shahrukh Khan",
          "nickname": "Shahrukh Khan",
          "iscaptain": false,
          "iskeeper": false,
          "outdec": "run out (Ravindra Jadeja/Dhruv Jurel)",
          "videotype": "",
          "videourl": "",
          "videoid": 0,
          "planid": 0,
          "imageid": 0,
          "premiumvideourl": "",
          "iscbplusfree": false,
          "ispremiumfree": false,
          "inmatchchange": "MIN",
          "isoverseas": false,
          "playingxichange": "OUT"
        },
        {
          "id": 10738,
          "balls": 16,
          "runs": 24,
          "fours": 3,
          "sixes": 0,
          "strkrate": "150",
          "name": "Rashid Khan",
          "nickname": "Rashid Khan",
          "iscaptain": true,
          "iskeeper": false,
          "outdec": "c Jofra Archer b Tushar Deshpande",
          "videotype": "",
          "videourl": "",
          "videoid": 0,
          "planid": 0,
          "imageid": 0,
          "premiumvideourl": "",
          "iscbplusfree": false,
          "ispremiumfree": false,
          "inmatchchange": "",
          "isoverseas": true,
          "playingxichange": ""
        },
        {
          "id": 9585,
          "balls": 16,
          "runs": 23,
          "fours": 1,
          "sixes": 2,
          "strkrate": "143.75",
          "name": "Kagiso Rabada",
          "nickname": "Kagiso Rabada",
          "iscaptain": false,
          "iskeeper": false,
          "outdec": "not out",
          "videotype": "",
          "videourl": "",
          "videoid": 0,
          "planid": 0,
          "imageid": 0,
          "premiumvideourl": "",
          "iscbplusfree": false,
          "ispremiumfree": false,
          "inmatchchange": "",
          "isoverseas": true,
          "playingxichange": ""
        },
        {
          "id": 24261,
          "balls": 1,
          "runs": 0,
          "fours": 0,
          "sixes": 0,
          "strkrate": "0",
          "name": "Ashok Sharma",
          "nickname": "Ashok Sharma",
          "iscaptain": false,
          "iskeeper": false,
          "outdec": "not out",
          "videotype": "",
          "videourl": "",
          "videoid": 0,
          "planid": 0,
          "imageid": 0,
          "premiumvideourl": "",
          "iscbplusfree": false,
          "ispremiumfree": false,
          "inmatchchange": "",
          "isoverseas": false,
          "playingxichange": ""
        },
        {
          "id": 10808,
          "balls": 0,
          "runs": 0,
          "fours": 0,
          "sixes": 0,
          "strkrate": "0",
          "name": "Mohammed Siraj",
          "nickname": "Mohammed Siraj",
          "iscaptain": false,
          "iskeeper": false,
          "outdec": "",
          "videotype": "",
          "videourl": "",
          "videoid": 0,
          "planid": 0,
          "imageid": 0,
          "premiumvideourl": "",
          "iscbplusfree": false,
          "ispremiumfree": false,
          "inmatchchange": "",
          "isoverseas": false,
          "playingxichange": ""
        },
        {
          "id": 10551,
          "balls": 0,
          "runs": 0,
          "fours": 0,
          "sixes": 0,
          "strkrate": "0",
          "name": "Prasidh Krishna",
          "nickname": "Prasidh Krishna",
          "iscaptain": false,
          "iskeeper": false,
          "outdec": "",
          "videotype": "",
          "videourl": "",
          "videoid": 0,
          "planid": 0,
          "imageid": 0,
          "premiumvideourl": "",
          "iscbplusfree": false,
          "ispremiumfree": false,
          "inmatchchange": "MOUT",
          "isoverseas": false,
          "playingxichange": ""
        }
      ],
      "bowler": [
        {
          "id": 11540,
          "overs": "4",
          "maidens": 0,
          "wickets": 0,
          "runs": 38,
          "economy": "9.5",
          "name": "Jofra Archer",
          "nickname": "Jofra Archer",
          "iscaptain": false,
          "iskeeper": false,
          "videotype": "",
          "videourl": "",
          "videoid": 0,
          "dots": 0,
          "balls": 40,
          "rpb": 0.95,
          "planid": 0,
          "imageid": 0,
          "premiumvideourl": "",
          "ispremiumfree": false,
          "inmatchchange": "",
          "isoverseas": true,
          "playingxichange": ""
        },
        {
          "id": 13630,
          "overs": "3",
          "maidens": 0,
          "wickets": 1,
          "runs": 29,
          "economy": "9.7",
          "name": "Nandre Burger",
          "nickname": "Nandre Burger",
          "iscaptain": false,
          "iskeeper": false,
          "videotype": "",
          "videourl": "",
          "videoid": 0,
          "dots": 0,
          "balls": 30,
          "rpb": 0.97,
          "planid": 0,
          "imageid": 0,
          "premiumvideourl": "",
          "ispremiumfree": false,
          "inmatchchange": "",
          "isoverseas": true,
          "playingxichange": ""
        },
        {
          "id": 8356,
          "overs": "3",
          "maidens": 0,
          "wickets": 0,
          "runs": 34,
          "economy": "11.3",
          "name": "Sandeep Sharma",
          "nickname": "Sandeep Sharma",
          "iscaptain": false,
          "iskeeper": false,
          "videotype": "",
          "videourl": "",
          "videoid": 0,
          "dots": 0,
          "balls": 30,
          "rpb": 1.13,
          "planid": 0,
          "imageid": 0,
          "premiumvideourl": "",
          "ispremiumfree": false,
          "inmatchchange": "",
          "isoverseas": false,
          "playingxichange": ""
        },
        {
          "id": 11307,
          "overs": "3",
          "maidens": 0,
          "wickets": 1,
          "runs": 24,
          "economy": "8",
          "name": "Tushar Deshpande",
          "nickname": "Tushar Deshpande",
          "iscaptain": false,
          "iskeeper": false,
          "videotype": "",
          "videourl": "",
          "videoid": 0,
          "dots": 0,
          "balls": 30,
          "rpb": 0.8,
          "planid": 0,
          "imageid": 0,
          "premiumvideourl": "",
          "ispremiumfree": false,
          "inmatchchange": "",
          "isoverseas": false,
          "playingxichange": "IN"
        },
        {
          "id": 587,
          "overs": "2",
          "maidens": 0,
          "wickets": 0,
          "runs": 25,
          "economy": "12.5",
          "name": "Ravindra Jadeja",
          "nickname": "Ravindra Jadeja",
          "iscaptain": false,
          "iskeeper": false,
          "videotype": "",
          "videourl": "",
          "videoid": 0,
          "dots": 0,
          "balls": 20,
          "rpb": 1.25,
          "planid": 0,
          "imageid": 0,
          "premiumvideourl": "",
          "ispremiumfree": false,
          "inmatchchange": "",
          "isoverseas": false,
          "playingxichange": ""
        },
        {
          "id": 12305,
          "overs": "1",
          "maidens": 0,
          "wickets": 1,
          "runs": 11,
          "economy": "11",
          "name": "Riyan Parag",
          "nickname": "Riyan Parag",
          "iscaptain": true,
          "iskeeper": false,
          "videotype": "",
          "videourl": "",
          "videoid": 0,
          "dots": 0,
          "balls": 10,
          "rpb": 1.1,
          "planid": 0,
          "imageid": 0,
          "premiumvideourl": "",
          "ispremiumfree": false,
          "inmatchchange": "",
          "isoverseas": false,
          "playingxichange": ""
        },
        {
          "id": 14659,
          "overs": "4",
          "maidens": 0,
          "wickets": 4,
          "runs": 41,
          "economy": "10.2",
          "name": "Ravi Bishnoi",
          "nickname": "Ravi Bishnoi",
          "iscaptain": false,
          "iskeeper": false,
          "videotype": "",
          "videourl": "",
          "videoid": 0,
          "dots": 0,
          "balls": 40,
          "rpb": 1.02,
          "planid": 0,
          "imageid": 0,
          "premiumvideourl": "",
          "ispremiumfree": false,
          "inmatchchange": "MIN",
          "isoverseas": false,
          "playingxichange": "OUT"
        }
      ],
      "fow": {
        "fow": [
          {
            "batsmanid": 15779,
            "batsmanname": "Kumar Kushagra",
            "overnbr": 7.6,
            "runs": 78,
            "ballnbr": 48
          },
          {
            "batsmanid": 13866,
            "batsmanname": "Sai Sudharsan",
            "overnbr": 10.4,
            "runs": 107,
            "ballnbr": 64
          },
          {
            "batsmanid": 10693,
            "batsmanname": "Glenn Phillips",
            "overnbr": 12.1,
            "runs": 127,
            "ballnbr": 73
          },
          {
            "batsmanid": 10945,
            "batsmanname": "Washington Sundar",
            "overnbr": 12.3,
            "runs": 131,
            "ballnbr": 75
          },
          {
            "batsmanid": 2258,
            "batsmanname": "Jos Buttler",
            "overnbr": 13.1,
            "runs": 133,
            "ballnbr": 79
          },
          {
            "batsmanid": 9693,
            "batsmanname": "Rahul Tewatia",
            "overnbr": 14.3,
            "runs": 155,
            "ballnbr": 87
          },
          {
            "batsmanid": 10226,
            "batsmanname": "Shahrukh Khan",
            "overnbr": 14.5,
            "runs": 161,
            "ballnbr": 89
          },
          {
            "batsmanid": 10738,
            "batsmanname": "Rashid Khan",
            "overnbr": 19.5,
            "runs": 204,
            "ballnbr": 119
          }
        ]
      },
      "extras": {
        "legbyes": 1,
        "byes": 1,
        "wides": 7,
        "noballs": 1,
        "penalty": 0,
        "total": 10
      },
      "score": 204,
      "wickets": 8,
      "overs": 20.0,
      "runrate": 10.2,
      "batteamname": "Gujarat Titans",
      "batteamsname": "GT",
      "isdeclared": false,
      "isfollowon": false,
      "ballnbr": 120,
      "rpb": 1.7,
      "partnership": {
        "partnership": [
          {
            "id": 0,
            "bat1id": 13866,
            "bat1name": "Sai Sudharsan",
            "bat1runs": 54,
            "bat1fours": 7,
            "bat1sixes": 2,
            "bat2id": 15779,
            "bat2name": "Kumar Kushagra",
            "bat2runs": 18,
            "bat2fours": 3,
            "bat2sixes": 0,
            "totalruns": 78,
            "totalballs": 48,
            "bat1balls": 34,
            "bat2balls": 14,
            "teamname": "",
            "teamid": 0,
            "bat1ones": 8,
            "bat1twos": 3,
            "bat1threes": 0,
            "bat1fives": 0,
            "bat1boundaries": 7,
            "bat1sixers": 2,
            "bat2ones": 4,
            "bat2twos": 1,
            "bat2threes": 0,
            "bat2fives": 0,
            "bat2boundaries": 3,
            "bat2sixers": 0
          },
          {
            "id": 0,
            "bat1id": 13866,
            "bat1name": "Sai Sudharsan",
            "bat1runs": 19,
            "bat1fours": 2,
            "bat1sixes": 1,
            "bat2id": 2258,
            "bat2name": "Jos Buttler",
            "bat2runs": 8,
            "bat2fours": 1,
            "bat2sixes": 0,
            "totalruns": 29,
            "totalballs": 16,
            "bat1balls": 10,
            "bat2balls": 7,
            "teamname": "",
            "teamid": 0,
            "bat1ones": 3,
            "bat1twos": 1,
            "bat1threes": 0,
            "bat1fives": 0,
            "bat1boundaries": 2,
            "bat1sixers": 1,
            "bat2ones": 4,
            "bat2twos": 0,
            "bat2threes": 0,
            "bat2fives": 0,
            "bat2boundaries": 1,
            "bat2sixers": 0
          },
          {
            "id": 0,
            "bat1id": 10693,
            "bat1name": "Glenn Phillips",
            "bat1runs": 3,
            "bat1fours": 0,
            "bat1sixes": 0,
            "bat2id": 2258,
            "bat2name": "Jos Buttler",
            "bat2runs": 17,
            "bat2fours": 4,
            "bat2sixes": 0,
            "totalruns": 20,
            "totalballs": 9,
            "bat1balls": 4,
            "bat2balls": 5,
            "teamname": "",
            "teamid": 0,
            "bat1ones": 3,
            "bat1twos": 0,
            "bat1threes": 0,
            "bat1fives": 0,
            "bat1boundaries": 0,
            "bat1sixers": 0,
            "bat2ones": 1,
            "bat2twos": 0,
            "bat2threes": 0,
            "bat2fives": 0,
            "bat2boundaries": 4,
            "bat2sixers": 0
          },
          {
            "id": 0,
            "bat1id": 10945,
            "bat1name": "Washington Sundar",
            "bat1runs": 4,
            "bat1fours": 1,
            "bat1sixes": 0,
            "bat2id": 2258,
            "bat2name": "Jos Buttler",
            "bat2runs": 0,
            "bat2fours": 0,
            "bat2sixes": 0,
            "totalruns": 4,
            "totalballs": 2,
            "bat1balls": 2,
            "bat2balls": 0,
            "teamname": "",
            "teamid": 0,
            "bat1ones": 0,
            "bat1twos": 0,
            "bat1threes": 0,
            "bat1fives": 0,
            "bat1boundaries": 1,
            "bat1sixers": 0,
            "bat2ones": 0,
            "bat2twos": 0,
            "bat2threes": 0,
            "bat2fives": 0,
            "bat2boundaries": 0,
            "bat2sixers": 0
          },
          {
            "id": 0,
            "bat1id": 9693,
            "bat1name": "Rahul Tewatia",
            "bat1runs": 1,
            "bat1fours": 0,
            "bat1sixes": 0,
            "bat2id": 2258,
            "bat2name": "Jos Buttler",
            "bat2runs": 1,
            "bat2fours": 0,
            "bat2sixes": 0,
            "totalruns": 2,
            "totalballs": 4,
            "bat1balls": 2,
            "bat2balls": 2,
            "teamname": "",
            "teamid": 0,
            "bat1ones": 1,
            "bat1twos": 0,
            "bat1threes": 0,
            "bat1fives": 0,
            "bat1boundaries": 0,
            "bat1sixers": 0,
            "bat2ones": 1,
            "bat2twos": 0,
            "bat2threes": 0,
            "bat2fives": 0,
            "bat2boundaries": 0,
            "bat2sixers": 0
          },
          {
            "id": 0,
            "bat1id": 9693,
            "bat1name": "Rahul Tewatia",
            "bat1runs": 11,
            "bat1fours": 1,
            "bat1sixes": 1,
            "bat2id": 10226,
            "bat2name": "Shahrukh Khan",
            "bat2runs": 11,
            "bat2fours": 1,
            "bat2sixes": 1,
            "totalruns": 22,
            "totalballs": 8,
            "bat1balls": 4,
            "bat2balls": 4,
            "teamname": "",
            "teamid": 0,
            "bat1ones": 1,
            "bat1twos": 0,
            "bat1threes": 0,
            "bat1fives": 0,
            "bat1boundaries": 1,
            "bat1sixers": 1,
            "bat2ones": 1,
            "bat2twos": 0,
            "bat2threes": 0,
            "bat2fives": 0,
            "bat2boundaries": 1,
            "bat2sixers": 1
          },
          {
            "id": 0,
            "bat1id": 10738,
            "bat1name": "Rashid Khan",
            "bat1runs": 6,
            "bat1fours": 1,
            "bat1sixes": 0,
            "bat2id": 10226,
            "bat2name": "Shahrukh Khan",
            "bat2runs": 0,
            "bat2fours": 0,
            "bat2sixes": 0,
            "totalruns": 6,
            "totalballs": 2,
            "bat1balls": 2,
            "bat2balls": 0,
            "teamname": "",
            "teamid": 0,
            "bat1ones": 0,
            "bat1twos": 1,
            "bat1threes": 0,
            "bat1fives": 0,
            "bat1boundaries": 1,
            "bat1sixers": 0,
            "bat2ones": 0,
            "bat2twos": 0,
            "bat2threes": 0,
            "bat2fives": 0,
            "bat2boundaries": 0,
            "bat2sixers": 0
          },
          {
            "id": 0,
            "bat1id": 10738,
            "bat1name": "Rashid Khan",
            "bat1runs": 18,
            "bat1fours": 2,
            "bat1sixes": 0,
            "bat2id": 9585,
            "bat2name": "Kagiso Rabada",
            "bat2runs": 23,
            "bat2fours": 1,
            "bat2sixes": 2,
            "totalruns": 43,
            "totalballs": 30,
            "bat1balls": 14,
            "bat2balls": 16,
            "teamname": "",
            "teamid": 0,
            "bat1ones": 8,
            "bat1twos": 1,
            "bat1threes": 0,
            "bat1fives": 0,
            "bat1boundaries": 2,
            "bat1sixers": 0,
            "bat2ones": 7,
            "bat2twos": 0,
            "bat2threes": 0,
            "bat2fives": 0,
            "bat2boundaries": 1,
            "bat2sixers": 2
          },
          {
            "id": 0,
            "bat1id": 24261,
            "bat1name": "Ashok Sharma",
            "bat1runs": 0,
            "bat1fours": 0,
            "bat1sixes": 0,
            "bat2id": 9585,
            "bat2name": "Kagiso Rabada",
            "bat2runs": 0,
            "bat2fours": 0,
            "bat2sixes": 0,
            "totalruns": 0,
            "totalballs": 1,
            "bat1balls": 1,
            "bat2balls": 0,
            "teamname": "",
            "teamid": 0,
            "bat1ones": 0,
            "bat1twos": 0,
            "bat1threes": 0,
            "bat1fives": 0,
            "bat1boundaries": 0,
            "bat1sixers": 0,
            "bat2ones": 0,
            "bat2twos": 0,
            "bat2threes": 0,
            "bat2fives": 0,
            "bat2boundaries": 0,
            "bat2sixers": 0
          }
        ]
      }
    }
  ],
  "ismatchcomplete": true,
  "appindex": {
    "seotitle": "Cricket scorecard - GT vs RR 9th Match,Indian Premier League 2026 | Cricbuzz.com",
    "weburl": "http://www.cricbuzz.com/live-cricket-scorecard/149699/gt-vs-rr-9th-match-indian-premier-league-2026"
  },
  "status": "Rajasthan Royals won by 6 runs",
  "responselastupdated": 1775412937,
  "man_of_the_match": "Ravi Bishnoi"
}