{
  "scorecard": [
    {
      "inningsid": 1,
      "batsman": [
        {
          "id": 12086,
          "balls": 28,
          "runs": 74,
          "fours": 5,
          "sixes": 8,
          "strkrate": "264.29",
          "name": "Abhishek Sharma",
          "nickname": "Abhishek Sharma",
          "iscaptain": false,
          "iskeeper": false,
          "outdec": "c Arshdeep Singh b Shashank Singh",
          "videotype": "",
          "videourl": "",
          "videoid": 0,
          "planid": 0,
          "imageid": 0,
          "premiumvideourl": "",
          "iscbplusfree": false,
          "ispremiumfree": false,
          "inmatchchange": "",
          "isoverseas": false,
          "playingxichange": ""
        },
        {
          "id": 8497,
          "balls": 23,
          "runs": 38,
          "fours": 5,
          "sixes": 1,
          "strkrate": "165.22",
          "name": "Travis Head",
          "nickname": "Travis Head",
          "iscaptain": false,
          "iskeeper": false,
          "outdec": "c Xavier Bartlett b Shashank Singh",
          "videotype": "",
          "videourl": "",
          "videoid": 0,
          "planid": 0,
          "imageid": 0,
          "premiumvideourl": "",
          "iscbplusfree": false,
          "ispremiumfree": false,
          "inmatchchange": "MOUT",
          "isoverseas": true,
          "playingxichange": ""
        },
        {
          "id": 10276,
          "balls": 17,
          "runs": 27,
          "fours": 3,
          "sixes": 1,
          "strkrate": "158.82",
          "name": "Ishan Kishan",
          "nickname": "Ishan Kishan",
          "iscaptain": true,
          "iskeeper": true,
          "outdec": "c Marco Jansen b Arshdeep Singh",
          "videotype": "",
          "videourl": "",
          "videoid": 0,
          "planid": 0,
          "imageid": 0,
          "premiumvideourl": "",
          "iscbplusfree": false,
          "ispremiumfree": false,
          "inmatchchange": "",
          "isoverseas": false,
          "playingxichange": ""
        },
        {
          "id": 10209,
          "balls": 33,
          "runs": 39,
          "fours": 1,
          "sixes": 1,
          "strkrate": "118.18",
          "name": "Heinrich Klaasen",
          "nickname": "Heinrich Klaasen",
          "iscaptain": false,
          "iskeeper": false,
          "outdec": "c Cooper Connolly b Xavier Bartlett",
          "videotype": "",
          "videourl": "",
          "videoid": 0,
          "planid": 0,
          "imageid": 0,
          "premiumvideourl": "",
          "iscbplusfree": false,
          "ispremiumfree": false,
          "inmatchchange": "",
          "isoverseas": true,
          "playingxichange": ""
        },
        {
          "id": 1447065,
          "balls": 9,
          "runs": 18,
          "fours": 1,
          "sixes": 1,
          "strkrate": "200",
          "name": "Aniket Verma",
          "nickname": "Aniket Verma",
          "iscaptain": false,
          "iskeeper": false,
          "outdec": "run out (Marcus Stoinis/Prabhsimran Singh)",
          "videotype": "",
          "videourl": "",
          "videoid": 0,
          "planid": 0,
          "imageid": 0,
          "premiumvideourl": "",
          "iscbplusfree": false,
          "ispremiumfree": false,
          "inmatchchange": "",
          "isoverseas": false,
          "playingxichange": ""
        },
        {
          "id": 15418,
          "balls": 8,
          "runs": 9,
          "fours": 0,
          "sixes": 1,
          "strkrate": "112.5",
          "name": "Salil Arora",
          "nickname": "Salil Arora",
          "iscaptain": false,
          "iskeeper": false,
          "outdec": "c Xavier Bartlett b Arshdeep Singh",
          "videotype": "",
          "videourl": "",
          "videoid": 0,
          "planid": 0,
          "imageid": 0,
          "premiumvideourl": "",
          "iscbplusfree": false,
          "ispremiumfree": false,
          "inmatchchange": "",
          "isoverseas": false,
          "playingxichange": "IN"
        },
        {
          "id": 14701,
          "balls": 1,
          "runs": 0,
          "fours": 0,
          "sixes": 0,
          "strkrate": "0",
          "name": "Nitish Kumar Reddy",
          "nickname": "Nitish Reddy",
          "iscaptain": false,
          "iskeeper": false,
          "outdec": "not out",
          "videotype": "",
          "videourl": "",
          "videoid": 0,
          "planid": 0,
          "imageid": 0,
          "premiumvideourl": "",
          "iscbplusfree": false,
          "ispremiumfree": false,
          "inmatchchange": "",
          "isoverseas": false,
          "playingxichange": ""
        },
        {
          "id": 14695,
          "balls": 2,
          "runs": 1,
          "fours": 0,
          "sixes": 0,
          "strkrate": "50",
          "name": "Harsh Dubey",
          "nickname": "Harsh Dubey",
          "iscaptain": false,
          "iskeeper": false,
          "outdec": "not out",
          "videotype": "",
          "videourl": "",
          "videoid": 0,
          "planid": 0,
          "imageid": 0,
          "premiumvideourl": "",
          "iscbplusfree": false,
          "ispremiumfree": false,
          "inmatchchange": "",
          "isoverseas": false,
          "playingxichange": ""
        },
        {
          "id": 1455907,
          "balls": 0,
          "runs": 0,
          "fours": 0,
          "sixes": 0,
          "strkrate": "0",
          "name": "Shivang Kumar",
          "nickname": "Shivang Kumar",
          "iscaptain": false,
          "iskeeper": false,
          "outdec": "",
          "videotype": "",
          "videourl": "",
          "videoid": 0,
          "planid": 0,
          "imageid": 0,
          "premiumvideourl": "",
          "iscbplusfree": false,
          "ispremiumfree": false,
          "inmatchchange": "",
          "isoverseas": false,
          "playingxichange": ""
        },
        {
          "id": 8175,
          "balls": 0,
          "runs": 0,
          "fours": 0,
          "sixes": 0,
          "strkrate": "0",
          "name": "Harshal Patel",
          "nickname": "Harshal Patel",
          "iscaptain": false,
          "iskeeper": false,
          "outdec": "",
          "videotype": "",
          "videourl": "",
          "videoid": 0,
          "planid": 0,
          "imageid": 0,
          "premiumvideourl": "",
          "iscbplusfree": false,
          "ispremiumfree": false,
          "inmatchchange": "",
          "isoverseas": false,
          "playingxichange": ""
        },
        {
          "id": 46926,
          "balls": 0,
          "runs": 0,
          "fours": 0,
          "sixes": 0,
          "strkrate": "0",
          "name": "Eshan Malinga",
          "nickname": "Eshan Malinga",
          "iscaptain": false,
          "iskeeper": false,
          "outdec": "",
          "videotype": "",
          "videourl": "",
          "videoid": 0,
          "planid": 0,
          "imageid": 0,
          "premiumvideourl": "",
          "iscbplusfree": false,
          "ispremiumfree": false,
          "inmatchchange": "",
          "isoverseas": true,
          "playingxichange": ""
        }
      ],
      "bowler": [
        {
          "id": 13217,
          "overs": "4",
          "maidens": 0,
          "wickets": 2,
          "runs": 50,
          "economy": "12.5",
          "name": "Arshdeep Singh",
          "nickname": "Arshdeep Singh",
          "iscaptain": false,
          "iskeeper": false,
          "videotype": "",
          "videourl": "",
          "videoid": 0,
          "dots": 0,
          "balls": 40,
          "rpb": 1.25,
          "planid": 0,
          "imageid": 0,
          "premiumvideourl": "",
          "ispremiumfree": false,
          "inmatchchange": "",
          "isoverseas": false,
          "playingxichange": ""
        },
        {
          "id": 11689,
          "overs": "4",
          "maidens": 0,
          "wickets": 1,
          "runs": 42,
          "economy": "10.5",
          "name": "Xavier Bartlett",
          "nickname": "Xavier Bartlett",
          "iscaptain": false,
          "iskeeper": false,
          "videotype": "",
          "videourl": "",
          "videoid": 0,
          "dots": 0,
          "balls": 40,
          "rpb": 1.05,
          "planid": 0,
          "imageid": 0,
          "premiumvideourl": "",
          "ispremiumfree": false,
          "inmatchchange": "",
          "isoverseas": true,
          "playingxichange": ""
        },
        {
          "id": 14565,
          "overs": "4",
          "maidens": 0,
          "wickets": 0,
          "runs": 40,
          "economy": "10",
          "name": "Marco Jansen",
          "nickname": "Marco Jansen",
          "iscaptain": false,
          "iskeeper": false,
          "videotype": "",
          "videourl": "",
          "videoid": 0,
          "dots": 0,
          "balls": 40,
          "rpb": 1.0,
          "planid": 0,
          "imageid": 0,
          "premiumvideourl": "",
          "ispremiumfree": false,
          "inmatchchange": "",
          "isoverseas": true,
          "playingxichange": ""
        },
        {
          "id": 10486,
          "overs": "2",
          "maidens": 0,
          "wickets": 0,
          "runs": 33,
          "economy": "16.5",
          "name": "Vijaykumar Vyshak",
          "nickname": "Vijaykumar Vyshak",
          "iscaptain": false,
          "iskeeper": false,
          "videotype": "",
          "videourl": "",
          "videoid": 0,
          "dots": 0,
          "balls": 20,
          "rpb": 1.65,
          "planid": 0,
          "imageid": 0,
          "premiumvideourl": "",
          "ispremiumfree": false,
          "inmatchchange": "",
          "isoverseas": false,
          "playingxichange": ""
        },
        {
          "id": 10919,
          "overs": "3",
          "maidens": 0,
          "wickets": 2,
          "runs": 20,
          "economy": "6.7",
          "name": "Shashank Singh",
          "nickname": "Shashank Singh",
          "iscaptain": false,
          "iskeeper": false,
          "videotype": "",
          "videourl": "",
          "videoid": 0,
          "dots": 0,
          "balls": 30,
          "rpb": 0.67,
          "planid": 0,
          "imageid": 0,
          "premiumvideourl": "",
          "ispremiumfree": false,
          "inmatchchange": "",
          "isoverseas": false,
          "playingxichange": ""
        },
        {
          "id": 7910,
          "overs": "3",
          "maidens": 0,
          "wickets": 0,
          "runs": 33,
          "economy": "11",
          "name": "Yuzvendra Chahal",
          "nickname": "Yuzvendra Chahal",
          "iscaptain": false,
          "iskeeper": false,
          "videotype": "",
          "videourl": "",
          "videoid": 0,
          "dots": 0,
          "balls": 30,
          "rpb": 1.1,
          "planid": 0,
          "imageid": 0,
          "premiumvideourl": "",
          "ispremiumfree": false,
          "inmatchchange": "MOUT",
          "isoverseas": false,
          "playingxichange": ""
        }
      ],
      "fow": {
        "fow": [
          {
            "batsmanid": 8497,
            "batsmanname": "Travis Head",
            "overnbr": 8.1,
            "runs": 120,
            "ballnbr": 49
          },
          {
            "batsmanid": 12086,
            "batsmanname": "Abhishek Sharma",
            "overnbr": 8.3,
            "runs": 122,
            "ballnbr": 51
          },
          {
            "batsmanid": 10276,
            "batsmanname": "Ishan Kishan",
            "overnbr": 13.6,
            "runs": 169,
            "ballnbr": 84
          },
          {
            "batsmanid": 1447065,
            "batsmanname": "Aniket Verma",
            "overnbr": 16.4,
            "runs": 195,
            "ballnbr": 100
          },
          {
            "batsmanid": 15418,
            "batsmanname": "Salil Arora",
            "overnbr": 18.5,
            "runs": 214,
            "ballnbr": 113
          },
          {
            "batsmanid": 10209,
            "batsmanname": "Heinrich Klaasen",
            "overnbr": 19.4,
            "runs": 218,
            "ballnbr": 118
          }
        ]
      },
      "extras": {
        "legbyes": 0,
        "byes": 1,
        "wides": 11,
        "noballs": 1,
        "penalty": 0,
        "total": 13
      },
      "score": 219,
      "wickets": 6,
      "overs": 20.0,
      "runrate": 10.95,
      "batteamname": "Sunrisers Hyderabad",
      "batteamsname": "SRH",
      "isdeclared": false,
      "isfollowon": false,
      "ballnbr": 120,
      "rpb": 1.83,
      "partnership": {
        "partnership": [
          {
            "id": 0,
            "bat1id": 12086,
            "bat1name": "Abhishek Sharma",
            "bat1runs": 74,
            "bat1fours": 5,
            "bat1sixes": 8,
            "bat2id": 8497,
            "bat2name": "Travis Head",
            "bat2runs": 38,
            "bat2fours": 5,
            "bat2sixes": 1,
            "totalruns": 120,
            "totalballs": 49,
            "bat1balls": 27,
            "bat2balls": 23,
            "teamname": "",
            "teamid": 0,
            "bat1ones": 6,
            "bat1twos": 0,
            "bat1threes": 0,
            "bat1fives": 0,
            "bat1boundaries": 5,
            "bat1sixers": 8,
            "bat2ones": 6,
            "bat2twos": 3,
            "bat2threes": 0,
            "bat2fives": 0,
            "bat2boundaries": 5,
            "bat2sixers": 1
          },
          {
            "id": 0,
            "bat1id": 12086,
            "bat1name": "Abhishek Sharma",
            "bat1runs": 0,
            "bat1fours": 0,
            "bat1sixes": 0,
            "bat2id": 10276,
            "bat2name": "Ishan Kishan",
            "bat2runs": 1,
            "bat2fours": 0,
            "bat2sixes": 0,
            "totalruns": 2,
            "totalballs": 2,
            "bat1balls": 1,
            "bat2balls": 1,
            "teamname": "",
            "teamid": 0,
            "bat1ones": 0,
            "bat1twos": 0,
            "bat1threes": 0,
            "bat1fives": 0,
            "bat1boundaries": 0,
            "bat1sixers": 0,
            "bat2ones": 1,
            "bat2twos": 0,
            "bat2threes": 0,
            "bat2fives": 0,
            "bat2boundaries": 0,
            "bat2sixers": 0
          },
          {
            "id": 0,
            "bat1id": 10209,
            "bat1name": "Heinrich Klaasen",
            "bat1runs": 18,
            "bat1fours": 1,
            "bat1sixes": 0,
            "bat2id": 10276,
            "bat2name": "Ishan Kishan",
            "bat2runs": 26,
            "bat2fours": 3,
            "bat2sixes": 1,
            "totalruns": 47,
            "totalballs": 33,
            "bat1balls": 17,
            "bat2balls": 16,
            "teamname": "",
            "teamid": 0,
            "bat1ones": 10,
            "bat1twos": 2,
            "bat1threes": 0,
            "bat1fives": 0,
            "bat1boundaries": 1,
            "bat1sixers": 0,
            "bat2ones": 8,
            "bat2twos": 0,
            "bat2threes": 0,
            "bat2fives": 0,
            "bat2boundaries": 3,
            "bat2sixers": 1
          },
          {
            "id": 0,
            "bat1id": 10209,
            "bat1name": "Heinrich Klaasen",
            "bat1runs": 8,
            "bat1fours": 0,
            "bat1sixes": 0,
            "bat2id": 1447065,
            "bat2name": "Aniket Verma",
            "bat2runs": 17,
            "bat2fours": 1,
            "bat2sixes": 1,
            "totalruns": 25,
            "totalballs": 16,
            "bat1balls": 7,
            "bat2balls": 9,
            "teamname": "",
            "teamid": 0,
            "bat1ones": 6,
            "bat1twos": 1,
            "bat1threes": 0,
            "bat1fives": 0,
            "bat1boundaries": 0,
            "bat1sixers": 0,
            "bat2ones": 5,
            "bat2twos": 1,
            "bat2threes": 0,
            "bat2fives": 0,
            "bat2boundaries": 1,
            "bat2sixers": 1
          },
          {
            "id": 0,
            "bat1id": 10209,
            "bat1name": "Heinrich Klaasen",
            "bat1runs": 9,
            "bat1fours": 0,
            "bat1sixes": 1,
            "bat2id": 15418,
            "bat2name": "Salil Arora",
            "bat2runs": 9,
            "bat2fours": 0,
            "bat2sixes": 1,
            "totalruns": 19,
            "totalballs": 13,
            "bat1balls": 5,
            "bat2balls": 8,
            "teamname": "",
            "teamid": 0,
            "bat1ones": 3,
            "bat1twos": 0,
            "bat1threes": 0,
            "bat1fives": 0,
            "bat1boundaries": 0,
            "bat1sixers": 1,
            "bat2ones": 3,
            "bat2twos": 0,
            "bat2threes": 0,
            "bat2fives": 0,
            "bat2boundaries": 0,
            "bat2sixers": 1
          },
          {
            "id": 0,
            "bat1id": 10209,
            "bat1name": "Heinrich Klaasen",
            "bat1runs": 10,
            "bat1fours": 0,
            "bat1sixes": 1,
            "bat2id": 14701,
            "bat2name": "Nitish Reddy",
            "bat2runs": 0,
            "bat2fours": 0,
            "bat2sixes": 0,
            "totalruns": 10,
            "totalballs": 5,
            "bat1balls": 4,
            "bat2balls": 1,
            "teamname": "",
            "teamid": 0,
            "bat1ones": 0,
            "bat1twos": 2,
            "bat1threes": 0,
            "bat1fives": 0,
            "bat1boundaries": 0,
            "bat1sixers": 1,
            "bat2ones": 0,
            "bat2twos": 0,
            "bat2threes": 0,
            "bat2fives": 0,
            "bat2boundaries": 0,
            "bat2sixers": 0
          },
          {
            "id": 0,
            "bat1id": 14695,
            "bat1name": "Harsh Dubey",
            "bat1runs": 1,
            "bat1fours": 0,
            "bat1sixes": 0,
            "bat2id": 14701,
            "bat2name": "Nitish Reddy",
            "bat2runs": 0,
            "bat2fours": 0,
            "bat2sixes": 0,
            "totalruns": 1,
            "totalballs": 2,
            "bat1balls": 2,
            "bat2balls": 0,
            "teamname": "",
            "teamid": 0,
            "bat1ones": 1,
            "bat1twos": 0,
            "bat1threes": 0,
            "bat1fives": 0,
            "bat1boundaries": 0,
            "bat1sixers": 0,
            "bat2ones": 0,
            "bat2twos": 0,
            "bat2threes": 0,
            "bat2fives": 0,
            "bat2boundaries": 0,
            "bat2sixers": 0
          }
        ]
      }
    },
    {
      "inningsid": 2,
      "batsman": [
        {
          "id": 14689,
          "balls": 20,
          "runs": 57,
          "fours": 5,
          "sixes": 5,
          "strkrate": "285",
          "name": "Priyansh Arya",
          "nickname": "Priyansh Arya",
          "iscaptain": false,
          "iskeeper": false,
          "outdec": "c Nitish Reddy b Shivang Kumar",
          "videotype": "",
          "videourl": "",
          "videoid": 0,
          "planid": 0,
          "imageid": 0,
          "premiumvideourl": "",
          "iscbplusfree": false,
          "ispremiumfree": false,
          "inmatchchange": "",
          "isoverseas": false,
          "playingxichange": "IN"
        },
        {
          "id": 14254,
          "balls": 25,
          "runs": 51,
          "fours": 4,
          "sixes": 4,
          "strkrate": "204",
          "name": "Prabhsimran Singh",
          "nickname": "Prabhsimran Singh",
          "iscaptain": false,
          "iskeeper": true,
          "outdec": "c Heinrich Klaasen b Shivang Kumar",
          "videotype": "",
          "videourl": "",
          "videoid": 0,
          "planid": 0,
          "imageid": 0,
          "premiumvideourl": "",
          "iscbplusfree": false,
          "ispremiumfree": false,
          "inmatchchange": "",
          "isoverseas": false,
          "playingxichange": ""
        },
        {
          "id": 15927,
          "balls": 12,
          "runs": 11,
          "fours": 1,
          "sixes": 0,
          "strkrate": "91.67",
          "name": "Cooper Connolly",
          "nickname": "Cooper Connolly",
          "iscaptain": false,
          "iskeeper": false,
          "outdec": "c Aniket Verma b Shivang Kumar",
          "videotype": "",
          "videourl": "",
          "videoid": 0,
          "planid": 0,
          "imageid": 0,
          "premiumvideourl": "",
          "iscbplusfree": false,
          "ispremiumfree": false,
          "inmatchchange": "",
          "isoverseas": true,
          "playingxichange": ""
        },
        {
          "id": 9428,
          "balls": 33,
          "runs": 69,
          "fours": 5,
          "sixes": 5,
          "strkrate": "209.09",
          "name": "Shreyas Iyer",
          "nickname": "Shreyas Iyer",
          "iscaptain": true,
          "iskeeper": false,
          "outdec": "not out",
          "videotype": "",
          "videourl": "",
          "videoid": 0,
          "planid": 0,
          "imageid": 0,
          "premiumvideourl": "",
          "iscbplusfree": false,
          "ispremiumfree": false,
          "inmatchchange": "",
          "isoverseas": false,
          "playingxichange": ""
        },
        {
          "id": 13915,
          "balls": 14,
          "runs": 14,
          "fours": 0,
          "sixes": 1,
          "strkrate": "100",
          "name": "Nehal Wadhera",
          "nickname": "Nehal Wadhera",
          "iscaptain": false,
          "iskeeper": false,
          "outdec": "b Harsh Dubey",
          "videotype": "",
          "videourl": "",
          "videoid": 0,
          "planid": 0,
          "imageid": 0,
          "premiumvideourl": "",
          "iscbplusfree": false,
          "ispremiumfree": false,
          "inmatchchange": "MIN",
          "isoverseas": false,
          "playingxichange": "OUT"
        },
        {
          "id": 10919,
          "balls": 9,
          "runs": 16,
          "fours": 1,
          "sixes": 1,
          "strkrate": "177.78",
          "name": "Shashank Singh",
          "nickname": "Shashank Singh",
          "iscaptain": false,
          "iskeeper": false,
          "outdec": "not out",
          "videotype": "",
          "videourl": "",
          "videoid": 0,
          "planid": 0,
          "imageid": 0,
          "premiumvideourl": "",
          "iscbplusfree": false,
          "ispremiumfree": false,
          "inmatchchange": "",
          "isoverseas": false,
          "playingxichange": ""
        },
        {
          "id": 8989,
          "balls": 0,
          "runs": 0,
          "fours": 0,
          "sixes": 0,
          "strkrate": "0",
          "name": "Marcus Stoinis",
          "nickname": "Marcus Stoinis",
          "iscaptain": false,
          "iskeeper": false,
          "outdec": "",
          "videotype": "",
          "videourl": "",
          "videoid": 0,
          "planid": 0,
          "imageid": 0,
          "premiumvideourl": "",
          "iscbplusfree": false,
          "ispremiumfree": false,
          "inmatchchange": "",
          "isoverseas": true,
          "playingxichange": ""
        },
        {
          "id": 14565,
          "balls": 0,
          "runs": 0,
          "fours": 0,
          "sixes": 0,
          "strkrate": "0",
          "name": "Marco Jansen",
          "nickname": "Marco Jansen",
          "iscaptain": false,
          "iskeeper": false,
          "outdec": "",
          "videotype": "",
          "videourl": "",
          "videoid": 0,
          "planid": 0,
          "imageid": 0,
          "premiumvideourl": "",
          "iscbplusfree": false,
          "ispremiumfree": false,
          "inmatchchange": "",
          "isoverseas": true,
          "playingxichange": ""
        },
        {
          "id": 11689,
          "balls": 0,
          "runs": 0,
          "fours": 0,
          "sixes": 0,
          "strkrate": "0",
          "name": "Xavier Bartlett",
          "nickname": "Xavier Bartlett",
          "iscaptain": false,
          "iskeeper": false,
          "outdec": "",
          "videotype": "",
          "videourl": "",
          "videoid": 0,
          "planid": 0,
          "imageid": 0,
          "premiumvideourl": "",
          "iscbplusfree": false,
          "ispremiumfree": false,
          "inmatchchange": "",
          "isoverseas": true,
          "playingxichange": ""
        },
        {
          "id": 10486,
          "balls": 0,
          "runs": 0,
          "fours": 0,
          "sixes": 0,
          "strkrate": "0",
          "name": "Vijaykumar Vyshak",
          "nickname": "Vijaykumar Vyshak",
          "iscaptain": false,
          "iskeeper": false,
          "outdec": "",
          "videotype": "",
          "videourl": "",
          "videoid": 0,
          "planid": 0,
          "imageid": 0,
          "premiumvideourl": "",
          "iscbplusfree": false,
          "ispremiumfree": false,
          "inmatchchange": "",
          "isoverseas": false,
          "playingxichange": ""
        },
        {
          "id": 13217,
          "balls": 0,
          "runs": 0,
          "fours": 0,
          "sixes": 0,
          "strkrate": "0",
          "name": "Arshdeep Singh",
          "nickname": "Arshdeep Singh",
          "iscaptain": false,
          "iskeeper": false,
          "outdec": "",
          "videotype": "",
          "videourl": "",
          "videoid": 0,
          "planid": 0,
          "imageid": 0,
          "premiumvideourl": "",
          "iscbplusfree": false,
          "ispremiumfree": false,
          "inmatchchange": "",
          "isoverseas": false,
          "playingxichange": ""
        },
        {
          "id": 7910,
          "balls": 0,
          "runs": 0,
          "fours": 0,
          "sixes": 0,
          "strkrate": "0",
          "name": "Yuzvendra Chahal",
          "nickname": "Yuzvendra Chahal",
          "iscaptain": false,
          "iskeeper": false,
          "outdec": "",
          "videotype": "",
          "videourl": "",
          "videoid": 0,
          "planid": 0,
          "imageid": 0,
          "premiumvideourl": "",
          "iscbplusfree": false,
          "ispremiumfree": false,
          "inmatchchange": "MOUT",
          "isoverseas": false,
          "playingxichange": ""
        }
      ],
      "bowler": [
        {
          "id": 14695,
          "overs": "4",
          "maidens": 0,
          "wickets": 1,
          "runs": 38,
          "economy": "9.5",
          "name": "Harsh Dubey",
          "nickname": "Harsh Dubey",
          "iscaptain": false,
          "iskeeper": false,
          "videotype": "",
          "videourl": "",
          "videoid": 0,
          "dots": 0,
          "balls": 40,
          "rpb": 0.95,
          "planid": 0,
          "imageid": 0,
          "premiumvideourl": "",
          "ispremiumfree": false,
          "inmatchchange": "",
          "isoverseas": false,
          "playingxichange": ""
        },
        {
          "id": 6327,
          "overs": "3",
          "maidens": 0,
          "wickets": 0,
          "runs": 40,
          "economy": "13.3",
          "name": "Jaydev Unadkat",
          "nickname": "Jaydev Unadkat",
          "iscaptain": false,
          "iskeeper": false,
          "videotype": "",
          "videourl": "",
          "videoid": 0,
          "dots": 0,
          "balls": 30,
          "rpb": 1.33,
          "planid": 0,
          "imageid": 0,
          "premiumvideourl": "",
          "ispremiumfree": false,
          "inmatchchange": "MIN",
          "isoverseas": false,
          "playingxichange": "OUT"
        },
        {
          "id": 46926,
          "overs": "3",
          "maidens": 0,
          "wickets": 0,
          "runs": 46,
          "economy": "15.3",
          "name": "Eshan Malinga",
          "nickname": "Eshan Malinga",
          "iscaptain": false,
          "iskeeper": false,
          "videotype": "",
          "videourl": "",
          "videoid": 0,
          "dots": 0,
          "balls": 30,
          "rpb": 1.53,
          "planid": 0,
          "imageid": 0,
          "premiumvideourl": "",
          "ispremiumfree": false,
          "inmatchchange": "",
          "isoverseas": true,
          "playingxichange": ""
        },
        {
          "id": 8175,
          "overs": "2",
          "maidens": 0,
          "wickets": 0,
          "runs": 39,
          "economy": "19.5",
          "name": "Harshal Patel",
          "nickname": "Harshal Patel",
          "iscaptain": false,
          "iskeeper": false,
          "videotype": "",
          "videourl": "",
          "videoid": 0,
          "dots": 0,
          "balls": 20,
          "rpb": 1.95,
          "planid": 0,
          "imageid": 0,
          "premiumvideourl": "",
          "ispremiumfree": false,
          "inmatchchange": "",
          "isoverseas": false,
          "playingxichange": ""
        },
        {
          "id": 1455907,
          "overs": "4",
          "maidens": 0,
          "wickets": 3,
          "runs": 33,
          "economy": "8.2",
          "name": "Shivang Kumar",
          "nickname": "Shivang Kumar",
          "iscaptain": false,
          "iskeeper": false,
          "videotype": "",
          "videourl": "",
          "videoid": 0,
          "dots": 0,
          "balls": 40,
          "rpb": 0.82,
          "planid": 0,
          "imageid": 0,
          "premiumvideourl": "",
          "ispremiumfree": false,
          "inmatchchange": "",
          "isoverseas": false,
          "playingxichange": ""
        },
        {
          "id": 14701,
          "overs": "2",
          "maidens": 0,
          "wickets": 0,
          "runs": 20,
          "economy": "10",
          "name": "Nitish Kumar Reddy",
          "nickname": "Nitish Reddy",
          "iscaptain": false,
          "iskeeper": false,
          "videotype": "",
          "videourl": "",
          "videoid": 0,
          "dots": 0,
          "balls": 20,
          "rpb": 1.0,
          "planid": 0,
          "imageid": 0,
          "premiumvideourl": "",
          "ispremiumfree": false,
          "inmatchchange": "",
          "isoverseas": false,
          "playingxichange": ""
        },
        {
          "id": 12086,
          "overs": "0.5",
          "maidens": 0,
          "wickets": 0,
          "runs": 7,
          "economy": "8.4",
          "name": "Abhishek Sharma",
          "nickname": "Abhishek Sharma",
          "iscaptain": false,
          "iskeeper": false,
          "videotype": "",
          "videourl": "",
          "videoid": 0,
          "dots": 0,
          "balls": 5,
          "rpb": 1.4,
          "planid": 0,
          "imageid": 0,
          "premiumvideourl": "",
          "ispremiumfree": false,
          "inmatchchange": "",
          "isoverseas": false,
          "playingxichange": ""
        }
      ],
      "fow": {
        "fow": [
          {
            "batsmanid": 14689,
            "batsmanname": "Priyansh Arya",
            "overnbr": 6.2,
            "runs": 99,
            "ballnbr": 38
          },
          {
            "batsmanid": 14254,
            "batsmanname": "Prabhsimran Singh",
            "overnbr": 8.5,
            "runs": 117,
            "ballnbr": 53
          },
          {
            "batsmanid": 15927,
            "batsmanname": "Cooper Connolly",
            "overnbr": 10.2,
            "runs": 128,
            "ballnbr": 62
          },
          {
            "batsmanid": 13915,
            "batsmanname": "Nehal Wadhera",
            "overnbr": 16.1,
            "runs": 197,
            "ballnbr": 97
          }
        ]
      },
      "extras": {
        "legbyes": 0,
        "byes": 0,
        "wides": 5,
        "noballs": 0,
        "penalty": 0,
        "total": 5
      },
      "score": 223,
      "wickets": 4,
      "overs": 18.5,
      "runrate": 11.84,
      "batteamname": "Punjab Kings",
      "batteamsname": "PBKS",
      "isdeclared": false,
      "isfollowon": false,
      "ballnbr": 113,
      "rpb": 1.97,
      "partnership": {
        "partnership": [
          {
            "id": 0,
            "bat1id": 14689,
            "bat1name": "Priyansh Arya",
            "bat1runs": 57,
            "bat1fours": 5,
            "bat1sixes": 5,
            "bat2id": 14254,
            "bat2name": "Prabhsimran Singh",
            "bat2runs": 41,
            "bat2fours": 3,
            "bat2sixes": 4,
            "totalruns": 99,
            "totalballs": 38,
            "bat1balls": 20,
            "bat2balls": 18,
            "teamname": "",
            "teamid": 0,
            "bat1ones": 3,
            "bat1twos": 2,
            "bat1threes": 0,
            "bat1fives": 0,
            "bat1boundaries": 5,
            "bat1sixers": 5,
            "bat2ones": 5,
            "bat2twos": 0,
            "bat2threes": 0,
            "bat2fives": 0,
            "bat2boundaries": 3,
            "bat2sixers": 4
          },
          {
            "id": 0,
            "bat1id": 15927,
            "bat1name": "Cooper Connolly",
            "bat1runs": 5,
            "bat1fours": 0,
            "bat1sixes": 0,
            "bat2id": 14254,
            "bat2name": "Prabhsimran Singh",
            "bat2runs": 10,
            "bat2fours": 1,
            "bat2sixes": 0,
            "totalruns": 18,
            "totalballs": 15,
            "bat1balls": 8,
            "bat2balls": 7,
            "teamname": "",
            "teamid": 0,
            "bat1ones": 5,
            "bat1twos": 0,
            "bat1threes": 0,
            "bat1fives": 0,
            "bat1boundaries": 0,
            "bat1sixers": 0,
            "bat2ones": 4,
            "bat2twos": 1,
            "bat2threes": 0,
            "bat2fives": 0,
            "bat2boundaries": 1,
            "bat2sixers": 0
          },
          {
            "id": 0,
            "bat1id": 15927,
            "bat1name": "Cooper Connolly",
            "bat1runs": 6,
            "bat1fours": 1,
            "bat1sixes": 0,
            "bat2id": 9428,
            "bat2name": "Shreyas Iyer",
            "bat2runs": 5,
            "bat2fours": 0,
            "bat2sixes": 0,
            "totalruns": 11,
            "totalballs": 9,
            "bat1balls": 4,
            "bat2balls": 5,
            "teamname": "",
            "teamid": 0,
            "bat1ones": 2,
            "bat1twos": 0,
            "bat1threes": 0,
            "bat1fives": 0,
            "bat1boundaries": 1,
            "bat1sixers": 0,
            "bat2ones": 3,
            "bat2twos": 1,
            "bat2threes": 0,
            "bat2fives": 0,
            "bat2boundaries": 0,
            "bat2sixers": 0
          },
          {
            "id": 0,
            "bat1id": 13915,
            "bat1name": "Nehal Wadhera",
            "bat1runs": 14,
            "bat1fours": 0,
            "bat1sixes": 1,
            "bat2id": 9428,
            "bat2name": "Shreyas Iyer",
            "bat2runs": 54,
            "bat2fours": 4,
            "bat2sixes": 5,
            "totalruns": 69,
            "totalballs": 35,
            "bat1balls": 14,
            "bat2balls": 21,
            "teamname": "",
            "teamid": 0,
            "bat1ones": 8,
            "bat1twos": 0,
            "bat1threes": 0,
            "bat1fives": 0,
            "bat1boundaries": 0,
            "bat1sixers": 1,
            "bat2ones": 8,
            "bat2twos": 0,
            "bat2threes": 0,
            "bat2fives": 0,
            "bat2boundaries": 4,
            "bat2sixers": 5
          },
          {
            "id": 0,
            "bat1id": 10919,
            "bat1name": "Shashank Singh",
            "bat1runs": 16,
            "bat1fours": 1,
            "bat1sixes": 1,
            "bat2id": 9428,
            "bat2name": "Shreyas Iyer",
            "bat2runs": 10,
            "bat2fours": 1,
            "bat2sixes": 0,
            "totalruns": 26,
            "totalballs": 16,
            "bat1balls": 9,
            "bat2balls": 7,
            "teamname": "",
            "teamid": 0,
            "bat1ones": 6,
            "bat1twos": 0,
            "bat1threes": 0,
            "bat1fives": 0,
            "bat1boundaries": 1,
            "bat1sixers": 1,
            "bat2ones": 6,
            "bat2twos": 0,
            "bat2threes": 0,
            "bat2fives": 0,
            "bat2boundaries": 1,
            "bat2sixers": 0
          }
        ]
      }
    }
  ],
  "ismatchcomplete": true,
  "appindex": {
    "seotitle": "Cricket scorecard - PBKS vs SRH 17th Match,Indian Premier League 2026 | Cricbuzz.com",
    "weburl": "http://www.cricbuzz.com/live-cricket-scorecard/149779/pbks-vs-srh-17th-match-indian-premier-league-2026"
  },
  "status": "Punjab Kings won by 6 wkts",
  "responselastupdated": 1775971452,
  "man_of_the_match": "Shreyas Iyer"
}