{
  "scorecard": [
    {
      "inningsid": 1,
      "batsman": [
        {
          "id": 9443,
          "balls": 14,
          "runs": 19,
          "fours": 2,
          "sixes": 1,
          "strkrate": "135.71",
          "name": "Tim Seifert",
          "nickname": "Tim Seifert",
          "iscaptain": false,
          "iskeeper": true,
          "outdec": "c Glenn Phillips b Kagiso Rabada",
          "videotype": "",
          "videourl": "",
          "videoid": 0,
          "planid": 0,
          "imageid": 0,
          "premiumvideourl": "",
          "iscbplusfree": false,
          "ispremiumfree": false,
          "inmatchchange": "",
          "isoverseas": true,
          "playingxichange": "IN"
        },
        {
          "id": 1447,
          "balls": 1,
          "runs": 0,
          "fours": 0,
          "sixes": 0,
          "strkrate": "0",
          "name": "Ajinkya Rahane",
          "nickname": "Ajinkya Rahane",
          "iscaptain": true,
          "iskeeper": false,
          "outdec": "c Kagiso Rabada b Mohammed Siraj",
          "videotype": "",
          "videourl": "",
          "videoid": 0,
          "planid": 0,
          "imageid": 0,
          "premiumvideourl": "",
          "iscbplusfree": false,
          "ispremiumfree": false,
          "inmatchchange": "",
          "isoverseas": false,
          "playingxichange": ""
        },
        {
          "id": 22566,
          "balls": 4,
          "runs": 8,
          "fours": 2,
          "sixes": 0,
          "strkrate": "200",
          "name": "Angkrish Raghuvanshi",
          "nickname": "Angkrish Raghuvanshi",
          "iscaptain": false,
          "iskeeper": false,
          "outdec": "c Jos Buttler b Kagiso Rabada",
          "videotype": "",
          "videourl": "",
          "videoid": 0,
          "planid": 0,
          "imageid": 0,
          "premiumvideourl": "",
          "iscbplusfree": false,
          "ispremiumfree": false,
          "inmatchchange": "MOUT",
          "isoverseas": false,
          "playingxichange": ""
        },
        {
          "id": 12225,
          "balls": 55,
          "runs": 79,
          "fours": 7,
          "sixes": 4,
          "strkrate": "143.64",
          "name": "Cameron Green",
          "nickname": "Cameron Green",
          "iscaptain": false,
          "iskeeper": false,
          "outdec": "c Jos Buttler b Rashid Khan",
          "videotype": "",
          "videourl": "",
          "videoid": 0,
          "planid": 0,
          "imageid": 0,
          "premiumvideourl": "",
          "iscbplusfree": false,
          "ispremiumfree": false,
          "inmatchchange": "",
          "isoverseas": true,
          "playingxichange": ""
        },
        {
          "id": 11445,
          "balls": 20,
          "runs": 27,
          "fours": 2,
          "sixes": 2,
          "strkrate": "135",
          "name": "Rovman Powell",
          "nickname": "Rovman Powell",
          "iscaptain": false,
          "iskeeper": false,
          "outdec": "c Mohammed Siraj b Ashok Sharma",
          "videotype": "",
          "videourl": "",
          "videoid": 0,
          "planid": 0,
          "imageid": 0,
          "premiumvideourl": "",
          "iscbplusfree": false,
          "ispremiumfree": false,
          "inmatchchange": "",
          "isoverseas": true,
          "playingxichange": ""
        },
        {
          "id": 12344,
          "balls": 7,
          "runs": 9,
          "fours": 1,
          "sixes": 0,
          "strkrate": "128.57",
          "name": "Anukul Roy",
          "nickname": "Anukul Roy",
          "iscaptain": false,
          "iskeeper": false,
          "outdec": "c Jos Buttler b Prasidh Krishna",
          "videotype": "",
          "videourl": "",
          "videoid": 0,
          "planid": 0,
          "imageid": 0,
          "premiumvideourl": "",
          "iscbplusfree": false,
          "ispremiumfree": false,
          "inmatchchange": "",
          "isoverseas": false,
          "playingxichange": ""
        },
        {
          "id": 10896,
          "balls": 2,
          "runs": 1,
          "fours": 0,
          "sixes": 0,
          "strkrate": "50",
          "name": "Rinku Singh",
          "nickname": "Rinku Singh",
          "iscaptain": false,
          "iskeeper": false,
          "outdec": "c Jos Buttler b Kagiso Rabada",
          "videotype": "",
          "videourl": "",
          "videoid": 0,
          "planid": 0,
          "imageid": 0,
          "premiumvideourl": "",
          "iscbplusfree": false,
          "ispremiumfree": false,
          "inmatchchange": "",
          "isoverseas": false,
          "playingxichange": ""
        },
        {
          "id": 12337,
          "balls": 8,
          "runs": 17,
          "fours": 2,
          "sixes": 1,
          "strkrate": "212.5",
          "name": "Ramandeep Singh",
          "nickname": "Ramandeep Singh",
          "iscaptain": false,
          "iskeeper": false,
          "outdec": "c Mohammed Siraj b Ashok Sharma",
          "videotype": "",
          "videourl": "",
          "videoid": 0,
          "planid": 0,
          "imageid": 0,
          "premiumvideourl": "",
          "iscbplusfree": false,
          "ispremiumfree": false,
          "inmatchchange": "",
          "isoverseas": false,
          "playingxichange": ""
        },
        {
          "id": 2276,
          "balls": 5,
          "runs": 0,
          "fours": 0,
          "sixes": 0,
          "strkrate": "0",
          "name": "Sunil Narine",
          "nickname": "Sunil Narine",
          "iscaptain": false,
          "iskeeper": false,
          "outdec": "c Glenn Phillips b Mohammed Siraj",
          "videotype": "",
          "videourl": "",
          "videoid": 0,
          "planid": 0,
          "imageid": 0,
          "premiumvideourl": "",
          "iscbplusfree": false,
          "ispremiumfree": false,
          "inmatchchange": "",
          "isoverseas": true,
          "playingxichange": ""
        },
        {
          "id": 13136,
          "balls": 4,
          "runs": 6,
          "fours": 0,
          "sixes": 1,
          "strkrate": "150",
          "name": "Kartik Tyagi",
          "nickname": "Kartik Tyagi",
          "iscaptain": false,
          "iskeeper": false,
          "outdec": "run out (Jos Buttler/Prasidh Krishna)",
          "videotype": "",
          "videourl": "",
          "videoid": 0,
          "planid": 0,
          "imageid": 0,
          "premiumvideourl": "",
          "iscbplusfree": false,
          "ispremiumfree": false,
          "inmatchchange": "",
          "isoverseas": false,
          "playingxichange": ""
        },
        {
          "id": 15861,
          "balls": 1,
          "runs": 0,
          "fours": 0,
          "sixes": 0,
          "strkrate": "0",
          "name": "Vaibhav Arora",
          "nickname": "Vaibhav Arora",
          "iscaptain": false,
          "iskeeper": false,
          "outdec": "not out",
          "videotype": "",
          "videourl": "",
          "videoid": 0,
          "planid": 0,
          "imageid": 0,
          "premiumvideourl": "",
          "iscbplusfree": false,
          "ispremiumfree": false,
          "inmatchchange": "",
          "isoverseas": false,
          "playingxichange": ""
        }
      ],
      "bowler": [
        {
          "id": 10808,
          "overs": "4",
          "maidens": 0,
          "wickets": 2,
          "runs": 23,
          "economy": "5.8",
          "name": "Mohammed Siraj",
          "nickname": "Mohammed Siraj",
          "iscaptain": false,
          "iskeeper": false,
          "videotype": "",
          "videourl": "",
          "videoid": 0,
          "dots": 0,
          "balls": 40,
          "rpb": 0.57,
          "planid": 0,
          "imageid": 0,
          "premiumvideourl": "",
          "ispremiumfree": false,
          "inmatchchange": "",
          "isoverseas": false,
          "playingxichange": ""
        },
        {
          "id": 9585,
          "overs": "4",
          "maidens": 0,
          "wickets": 3,
          "runs": 29,
          "economy": "7.2",
          "name": "Kagiso Rabada",
          "nickname": "Kagiso Rabada",
          "iscaptain": false,
          "iskeeper": false,
          "videotype": "",
          "videourl": "",
          "videoid": 0,
          "dots": 0,
          "balls": 40,
          "rpb": 0.72,
          "planid": 0,
          "imageid": 0,
          "premiumvideourl": "",
          "ispremiumfree": false,
          "inmatchchange": "",
          "isoverseas": true,
          "playingxichange": ""
        },
        {
          "id": 10551,
          "overs": "4",
          "maidens": 0,
          "wickets": 1,
          "runs": 32,
          "economy": "8",
          "name": "Prasidh Krishna",
          "nickname": "Prasidh Krishna",
          "iscaptain": false,
          "iskeeper": false,
          "videotype": "",
          "videourl": "",
          "videoid": 0,
          "dots": 0,
          "balls": 40,
          "rpb": 0.8,
          "planid": 0,
          "imageid": 0,
          "premiumvideourl": "",
          "ispremiumfree": false,
          "inmatchchange": "MOUT",
          "isoverseas": false,
          "playingxichange": ""
        },
        {
          "id": 24261,
          "overs": "4",
          "maidens": 0,
          "wickets": 2,
          "runs": 45,
          "economy": "11.2",
          "name": "Ashok Sharma",
          "nickname": "Ashok Sharma",
          "iscaptain": false,
          "iskeeper": false,
          "videotype": "",
          "videourl": "",
          "videoid": 0,
          "dots": 0,
          "balls": 40,
          "rpb": 1.12,
          "planid": 0,
          "imageid": 0,
          "premiumvideourl": "",
          "ispremiumfree": false,
          "inmatchchange": "",
          "isoverseas": false,
          "playingxichange": ""
        },
        {
          "id": 10738,
          "overs": "4",
          "maidens": 0,
          "wickets": 1,
          "runs": 44,
          "economy": "11",
          "name": "Rashid Khan",
          "nickname": "Rashid Khan",
          "iscaptain": false,
          "iskeeper": false,
          "videotype": "",
          "videourl": "",
          "videoid": 0,
          "dots": 0,
          "balls": 40,
          "rpb": 1.1,
          "planid": 0,
          "imageid": 0,
          "premiumvideourl": "",
          "ispremiumfree": false,
          "inmatchchange": "",
          "isoverseas": true,
          "playingxichange": ""
        }
      ],
      "fow": {
        "fow": [
          {
            "batsmanid": 1447,
            "batsmanname": "Ajinkya Rahane",
            "overnbr": 0.4,
            "runs": 5,
            "ballnbr": 4
          },
          {
            "batsmanid": 22566,
            "batsmanname": "Angkrish Raghuvanshi",
            "overnbr": 1.6,
            "runs": 21,
            "ballnbr": 12
          },
          {
            "batsmanid": 9443,
            "batsmanname": "Tim Seifert",
            "overnbr": 3.6,
            "runs": 32,
            "ballnbr": 24
          },
          {
            "batsmanid": 11445,
            "batsmanname": "Rovman Powell",
            "overnbr": 10.6,
            "runs": 87,
            "ballnbr": 66
          },
          {
            "batsmanid": 12344,
            "batsmanname": "Anukul Roy",
            "overnbr": 14.5,
            "runs": 147,
            "ballnbr": 89
          },
          {
            "batsmanid": 10896,
            "batsmanname": "Rinku Singh",
            "overnbr": 15.1,
            "runs": 148,
            "ballnbr": 91
          },
          {
            "batsmanid": 12337,
            "batsmanname": "Ramandeep Singh",
            "overnbr": 16.3,
            "runs": 165,
            "ballnbr": 99
          },
          {
            "batsmanid": 2276,
            "batsmanname": "Sunil Narine",
            "overnbr": 17.3,
            "runs": 166,
            "ballnbr": 105
          },
          {
            "batsmanid": 13136,
            "batsmanname": "Kartik Tyagi",
            "overnbr": 18.2,
            "runs": 173,
            "ballnbr": 110
          },
          {
            "batsmanid": 12225,
            "batsmanname": "Cameron Green",
            "overnbr": 19.6,
            "runs": 180,
            "ballnbr": 120
          }
        ]
      },
      "extras": {
        "legbyes": 3,
        "byes": 4,
        "wides": 6,
        "noballs": 1,
        "penalty": 0,
        "total": 14
      },
      "score": 180,
      "wickets": 10,
      "overs": 20.0,
      "runrate": 9.0,
      "batteamname": "Kolkata Knight Riders",
      "batteamsname": "KKR",
      "isdeclared": false,
      "isfollowon": false,
      "ballnbr": 120,
      "rpb": 1.5,
      "partnership": {
        "partnership": [
          {
            "id": 0,
            "bat1id": 9443,
            "bat1name": "Tim Seifert",
            "bat1runs": 5,
            "bat1fours": 1,
            "bat1sixes": 0,
            "bat2id": 1447,
            "bat2name": "Ajinkya Rahane",
            "bat2runs": 0,
            "bat2fours": 0,
            "bat2sixes": 0,
            "totalruns": 5,
            "totalballs": 4,
            "bat1balls": 3,
            "bat2balls": 1,
            "teamname": "",
            "teamid": 0,
            "bat1ones": 1,
            "bat1twos": 0,
            "bat1threes": 0,
            "bat1fives": 0,
            "bat1boundaries": 1,
            "bat1sixers": 0,
            "bat2ones": 0,
            "bat2twos": 0,
            "bat2threes": 0,
            "bat2fives": 0,
            "bat2boundaries": 0,
            "bat2sixers": 0
          },
          {
            "id": 0,
            "bat1id": 9443,
            "bat1name": "Tim Seifert",
            "bat1runs": 7,
            "bat1fours": 0,
            "bat1sixes": 1,
            "bat2id": 22566,
            "bat2name": "Angkrish Raghuvanshi",
            "bat2runs": 8,
            "bat2fours": 2,
            "bat2sixes": 0,
            "totalruns": 16,
            "totalballs": 8,
            "bat1balls": 4,
            "bat2balls": 4,
            "teamname": "",
            "teamid": 0,
            "bat1ones": 1,
            "bat1twos": 0,
            "bat1threes": 0,
            "bat1fives": 0,
            "bat1boundaries": 0,
            "bat1sixers": 1,
            "bat2ones": 0,
            "bat2twos": 0,
            "bat2threes": 0,
            "bat2fives": 0,
            "bat2boundaries": 2,
            "bat2sixers": 0
          },
          {
            "id": 0,
            "bat1id": 9443,
            "bat1name": "Tim Seifert",
            "bat1runs": 7,
            "bat1fours": 1,
            "bat1sixes": 0,
            "bat2id": 12225,
            "bat2name": "Cameron Green",
            "bat2runs": 3,
            "bat2fours": 0,
            "bat2sixes": 0,
            "totalruns": 11,
            "totalballs": 12,
            "bat1balls": 7,
            "bat2balls": 5,
            "teamname": "",
            "teamid": 0,
            "bat1ones": 3,
            "bat1twos": 0,
            "bat1threes": 0,
            "bat1fives": 0,
            "bat1boundaries": 1,
            "bat1sixers": 0,
            "bat2ones": 1,
            "bat2twos": 1,
            "bat2threes": 0,
            "bat2fives": 0,
            "bat2boundaries": 0,
            "bat2sixers": 0
          },
          {
            "id": 0,
            "bat1id": 11445,
            "bat1name": "Rovman Powell",
            "bat1runs": 27,
            "bat1fours": 2,
            "bat1sixes": 2,
            "bat2id": 12225,
            "bat2name": "Cameron Green",
            "bat2runs": 24,
            "bat2fours": 3,
            "bat2sixes": 0,
            "totalruns": 55,
            "totalballs": 42,
            "bat1balls": 20,
            "bat2balls": 23,
            "teamname": "",
            "teamid": 0,
            "bat1ones": 5,
            "bat1twos": 1,
            "bat1threes": 0,
            "bat1fives": 0,
            "bat1boundaries": 2,
            "bat1sixers": 2,
            "bat2ones": 6,
            "bat2twos": 3,
            "bat2threes": 0,
            "bat2fives": 0,
            "bat2boundaries": 3,
            "bat2sixers": 0
          },
          {
            "id": 0,
            "bat1id": 12344,
            "bat1name": "Anukul Roy",
            "bat1runs": 9,
            "bat1fours": 1,
            "bat1sixes": 0,
            "bat2id": 12225,
            "bat2name": "Cameron Green",
            "bat2runs": 48,
            "bat2fours": 4,
            "bat2sixes": 4,
            "totalruns": 60,
            "totalballs": 23,
            "bat1balls": 7,
            "bat2balls": 16,
            "teamname": "",
            "teamid": 0,
            "bat1ones": 3,
            "bat1twos": 1,
            "bat1threes": 0,
            "bat1fives": 0,
            "bat1boundaries": 1,
            "bat1sixers": 0,
            "bat2ones": 4,
            "bat2twos": 2,
            "bat2threes": 0,
            "bat2fives": 0,
            "bat2boundaries": 4,
            "bat2sixers": 4
          },
          {
            "id": 0,
            "bat1id": 10896,
            "bat1name": "Rinku Singh",
            "bat1runs": 1,
            "bat1fours": 0,
            "bat1sixes": 0,
            "bat2id": 12225,
            "bat2name": "Cameron Green",
            "bat2runs": 0,
            "bat2fours": 0,
            "bat2sixes": 0,
            "totalruns": 1,
            "totalballs": 2,
            "bat1balls": 2,
            "bat2balls": 0,
            "teamname": "",
            "teamid": 0,
            "bat1ones": 1,
            "bat1twos": 0,
            "bat1threes": 0,
            "bat1fives": 0,
            "bat1boundaries": 0,
            "bat1sixers": 0,
            "bat2ones": 0,
            "bat2twos": 0,
            "bat2threes": 0,
            "bat2fives": 0,
            "bat2boundaries": 0,
            "bat2sixers": 0
          },
          {
            "id": 0,
            "bat1id": 12337,
            "bat1name": "Ramandeep Singh",
            "bat1runs": 17,
            "bat1fours": 2,
            "bat1sixes": 1,
            "bat2id": 12225,
            "bat2name": "Cameron Green",
            "bat2runs": 0,
            "bat2fours": 0,
            "bat2sixes": 0,
            "totalruns": 17,
            "totalballs": 8,
            "bat1balls": 8,
            "bat2balls": 0,
            "teamname": "",
            "teamid": 0,
            "bat1ones": 1,
            "bat1twos": 1,
            "bat1threes": 0,
            "bat1fives": 0,
            "bat1boundaries": 2,
            "bat1sixers": 1,
            "bat2ones": 0,
            "bat2twos": 0,
            "bat2threes": 0,
            "bat2fives": 0,
            "bat2boundaries": 0,
            "bat2sixers": 0
          },
          {
            "id": 0,
            "bat1id": 2276,
            "bat1name": "Sunil Narine",
            "bat1runs": 0,
            "bat1fours": 0,
            "bat1sixes": 0,
            "bat2id": 12225,
            "bat2name": "Cameron Green",
            "bat2runs": 1,
            "bat2fours": 0,
            "bat2sixes": 0,
            "totalruns": 1,
            "totalballs": 6,
            "bat1balls": 5,
            "bat2balls": 1,
            "teamname": "",
            "teamid": 0,
            "bat1ones": 0,
            "bat1twos": 0,
            "bat1threes": 0,
            "bat1fives": 0,
            "bat1boundaries": 0,
            "bat1sixers": 0,
            "bat2ones": 1,
            "bat2twos": 0,
            "bat2threes": 0,
            "bat2fives": 0,
            "bat2boundaries": 0,
            "bat2sixers": 0
          },
          {
            "id": 0,
            "bat1id": 13136,
            "bat1name": "Kartik Tyagi",
            "bat1runs": 6,
            "bat1fours": 0,
            "bat1sixes": 1,
            "bat2id": 12225,
            "bat2name": "Cameron Green",
            "bat2runs": 1,
            "bat2fours": 0,
            "bat2sixes": 0,
            "totalruns": 7,
            "totalballs": 5,
            "bat1balls": 4,
            "bat2balls": 1,
            "teamname": "",
            "teamid": 0,
            "bat1ones": 0,
            "bat1twos": 0,
            "bat1threes": 0,
            "bat1fives": 0,
            "bat1boundaries": 0,
            "bat1sixers": 1,
            "bat2ones": 1,
            "bat2twos": 0,
            "bat2threes": 0,
            "bat2fives": 0,
            "bat2boundaries": 0,
            "bat2sixers": 0
          },
          {
            "id": 0,
            "bat1id": 15861,
            "bat1name": "Vaibhav Arora",
            "bat1runs": 0,
            "bat1fours": 0,
            "bat1sixes": 0,
            "bat2id": 12225,
            "bat2name": "Cameron Green",
            "bat2runs": 2,
            "bat2fours": 0,
            "bat2sixes": 0,
            "totalruns": 7,
            "totalballs": 10,
            "bat1balls": 1,
            "bat2balls": 9,
            "teamname": "",
            "teamid": 0,
            "bat1ones": 0,
            "bat1twos": 0,
            "bat1threes": 0,
            "bat1fives": 0,
            "bat1boundaries": 0,
            "bat1sixers": 0,
            "bat2ones": 2,
            "bat2twos": 0,
            "bat2threes": 0,
            "bat2fives": 0,
            "bat2boundaries": 0,
            "bat2sixers": 0
          }
        ]
      }
    },
    {
      "inningsid": 2,
      "batsman": [
        {
          "id": 13866,
          "balls": 16,
          "runs": 22,
          "fours": 1,
          "sixes": 2,
          "strkrate": "137.5",
          "name": "Sai Sudharsan",
          "nickname": "Sai Sudharsan",
          "iscaptain": false,
          "iskeeper": false,
          "outdec": "c Kartik Tyagi b Sunil Narine",
          "videotype": "",
          "videourl": "",
          "videoid": 0,
          "planid": 0,
          "imageid": 0,
          "premiumvideourl": "",
          "iscbplusfree": false,
          "ispremiumfree": false,
          "inmatchchange": "",
          "isoverseas": false,
          "playingxichange": ""
        },
        {
          "id": 11808,
          "balls": 50,
          "runs": 86,
          "fours": 8,
          "sixes": 4,
          "strkrate": "172",
          "name": "Shubman Gill",
          "nickname": "Shubman Gill",
          "iscaptain": true,
          "iskeeper": false,
          "outdec": "c Cameron Green b Vaibhav Arora",
          "videotype": "",
          "videourl": "",
          "videoid": 0,
          "planid": 0,
          "imageid": 0,
          "premiumvideourl": "",
          "iscbplusfree": false,
          "ispremiumfree": false,
          "inmatchchange": "",
          "isoverseas": false,
          "playingxichange": ""
        },
        {
          "id": 2258,
          "balls": 15,
          "runs": 25,
          "fours": 2,
          "sixes": 2,
          "strkrate": "166.67",
          "name": "Jos Buttler",
          "nickname": "Jos Buttler",
          "iscaptain": false,
          "iskeeper": true,
          "outdec": "c Cameron Green b Varun Chakaravarthy",
          "videotype": "",
          "videourl": "",
          "videoid": 0,
          "planid": 0,
          "imageid": 0,
          "premiumvideourl": "",
          "iscbplusfree": false,
          "ispremiumfree": false,
          "inmatchchange": "",
          "isoverseas": true,
          "playingxichange": ""
        },
        {
          "id": 10945,
          "balls": 13,
          "runs": 13,
          "fours": 1,
          "sixes": 0,
          "strkrate": "100",
          "name": "Washington Sundar",
          "nickname": "Washington Sundar",
          "iscaptain": false,
          "iskeeper": false,
          "outdec": "c Kartik Tyagi b Varun Chakaravarthy",
          "videotype": "",
          "videourl": "",
          "videoid": 0,
          "planid": 0,
          "imageid": 0,
          "premiumvideourl": "",
          "iscbplusfree": false,
          "ispremiumfree": false,
          "inmatchchange": "",
          "isoverseas": false,
          "playingxichange": ""
        },
        {
          "id": 10693,
          "balls": 16,
          "runs": 19,
          "fours": 2,
          "sixes": 0,
          "strkrate": "118.75",
          "name": "Glenn Phillips",
          "nickname": "Glenn Phillips",
          "iscaptain": false,
          "iskeeper": false,
          "outdec": "c Rinku Singh b Ramandeep Singh",
          "videotype": "",
          "videourl": "",
          "videoid": 0,
          "planid": 0,
          "imageid": 0,
          "premiumvideourl": "",
          "iscbplusfree": false,
          "ispremiumfree": false,
          "inmatchchange": "",
          "isoverseas": true,
          "playingxichange": ""
        },
        {
          "id": 9693,
          "balls": 6,
          "runs": 7,
          "fours": 0,
          "sixes": 0,
          "strkrate": "116.67",
          "name": "Rahul Tewatia",
          "nickname": "Rahul Tewatia",
          "iscaptain": false,
          "iskeeper": false,
          "outdec": "not out",
          "videotype": "",
          "videourl": "",
          "videoid": 0,
          "planid": 0,
          "imageid": 0,
          "premiumvideourl": "",
          "iscbplusfree": false,
          "ispremiumfree": false,
          "inmatchchange": "",
          "isoverseas": false,
          "playingxichange": ""
        },
        {
          "id": 10226,
          "balls": 2,
          "runs": 3,
          "fours": 0,
          "sixes": 0,
          "strkrate": "150",
          "name": "Shahrukh Khan",
          "nickname": "Shahrukh Khan",
          "iscaptain": false,
          "iskeeper": false,
          "outdec": "not out",
          "videotype": "",
          "videourl": "",
          "videoid": 0,
          "planid": 0,
          "imageid": 0,
          "premiumvideourl": "",
          "iscbplusfree": false,
          "ispremiumfree": false,
          "inmatchchange": "MIN",
          "isoverseas": false,
          "playingxichange": "OUT"
        },
        {
          "id": 10738,
          "balls": 0,
          "runs": 0,
          "fours": 0,
          "sixes": 0,
          "strkrate": "0",
          "name": "Rashid Khan",
          "nickname": "Rashid Khan",
          "iscaptain": false,
          "iskeeper": false,
          "outdec": "",
          "videotype": "",
          "videourl": "",
          "videoid": 0,
          "planid": 0,
          "imageid": 0,
          "premiumvideourl": "",
          "iscbplusfree": false,
          "ispremiumfree": false,
          "inmatchchange": "",
          "isoverseas": true,
          "playingxichange": ""
        },
        {
          "id": 24261,
          "balls": 0,
          "runs": 0,
          "fours": 0,
          "sixes": 0,
          "strkrate": "0",
          "name": "Ashok Sharma",
          "nickname": "Ashok Sharma",
          "iscaptain": false,
          "iskeeper": false,
          "outdec": "",
          "videotype": "",
          "videourl": "",
          "videoid": 0,
          "planid": 0,
          "imageid": 0,
          "premiumvideourl": "",
          "iscbplusfree": false,
          "ispremiumfree": false,
          "inmatchchange": "",
          "isoverseas": false,
          "playingxichange": ""
        },
        {
          "id": 9585,
          "balls": 0,
          "runs": 0,
          "fours": 0,
          "sixes": 0,
          "strkrate": "0",
          "name": "Kagiso Rabada",
          "nickname": "Kagiso Rabada",
          "iscaptain": false,
          "iskeeper": false,
          "outdec": "",
          "videotype": "",
          "videourl": "",
          "videoid": 0,
          "planid": 0,
          "imageid": 0,
          "premiumvideourl": "",
          "iscbplusfree": false,
          "ispremiumfree": false,
          "inmatchchange": "",
          "isoverseas": true,
          "playingxichange": ""
        },
        {
          "id": 10808,
          "balls": 0,
          "runs": 0,
          "fours": 0,
          "sixes": 0,
          "strkrate": "0",
          "name": "Mohammed Siraj",
          "nickname": "Mohammed Siraj",
          "iscaptain": false,
          "iskeeper": false,
          "outdec": "",
          "videotype": "",
          "videourl": "",
          "videoid": 0,
          "planid": 0,
          "imageid": 0,
          "premiumvideourl": "",
          "iscbplusfree": false,
          "ispremiumfree": false,
          "inmatchchange": "",
          "isoverseas": false,
          "playingxichange": ""
        },
        {
          "id": 10551,
          "balls": 0,
          "runs": 0,
          "fours": 0,
          "sixes": 0,
          "strkrate": "0",
          "name": "Prasidh Krishna",
          "nickname": "Prasidh Krishna",
          "iscaptain": false,
          "iskeeper": false,
          "outdec": "",
          "videotype": "",
          "videourl": "",
          "videoid": 0,
          "planid": 0,
          "imageid": 0,
          "premiumvideourl": "",
          "iscbplusfree": false,
          "ispremiumfree": false,
          "inmatchchange": "MOUT",
          "isoverseas": false,
          "playingxichange": ""
        }
      ],
      "bowler": [
        {
          "id": 15861,
          "overs": "4",
          "maidens": 0,
          "wickets": 1,
          "runs": 35,
          "economy": "8.8",
          "name": "Vaibhav Arora",
          "nickname": "Vaibhav Arora",
          "iscaptain": false,
          "iskeeper": false,
          "videotype": "",
          "videourl": "",
          "videoid": 0,
          "dots": 0,
          "balls": 40,
          "rpb": 0.88,
          "planid": 0,
          "imageid": 0,
          "premiumvideourl": "",
          "ispremiumfree": false,
          "inmatchchange": "",
          "isoverseas": false,
          "playingxichange": ""
        },
        {
          "id": 13136,
          "overs": "4",
          "maidens": 0,
          "wickets": 0,
          "runs": 40,
          "economy": "10",
          "name": "Kartik Tyagi",
          "nickname": "Kartik Tyagi",
          "iscaptain": false,
          "iskeeper": false,
          "videotype": "",
          "videourl": "",
          "videoid": 0,
          "dots": 0,
          "balls": 40,
          "rpb": 1.0,
          "planid": 0,
          "imageid": 0,
          "premiumvideourl": "",
          "ispremiumfree": false,
          "inmatchchange": "",
          "isoverseas": false,
          "playingxichange": ""
        },
        {
          "id": 12344,
          "overs": "3",
          "maidens": 0,
          "wickets": 0,
          "runs": 37,
          "economy": "12.3",
          "name": "Anukul Roy",
          "nickname": "Anukul Roy",
          "iscaptain": false,
          "iskeeper": false,
          "videotype": "",
          "videourl": "",
          "videoid": 0,
          "dots": 0,
          "balls": 30,
          "rpb": 1.23,
          "planid": 0,
          "imageid": 0,
          "premiumvideourl": "",
          "ispremiumfree": false,
          "inmatchchange": "",
          "isoverseas": false,
          "playingxichange": ""
        },
        {
          "id": 2276,
          "overs": "4",
          "maidens": 0,
          "wickets": 1,
          "runs": 28,
          "economy": "7",
          "name": "Sunil Narine",
          "nickname": "Sunil Narine",
          "iscaptain": false,
          "iskeeper": false,
          "videotype": "",
          "videourl": "",
          "videoid": 0,
          "dots": 0,
          "balls": 40,
          "rpb": 0.7,
          "planid": 0,
          "imageid": 0,
          "premiumvideourl": "",
          "ispremiumfree": false,
          "inmatchchange": "",
          "isoverseas": true,
          "playingxichange": ""
        },
        {
          "id": 12926,
          "overs": "4",
          "maidens": 0,
          "wickets": 2,
          "runs": 34,
          "economy": "8.5",
          "name": "Varun Chakaravarthy",
          "nickname": "Varun Chakaravarthy",
          "iscaptain": false,
          "iskeeper": false,
          "videotype": "",
          "videourl": "",
          "videoid": 0,
          "dots": 0,
          "balls": 40,
          "rpb": 0.85,
          "planid": 0,
          "imageid": 0,
          "premiumvideourl": "",
          "ispremiumfree": false,
          "inmatchchange": "MIN",
          "isoverseas": false,
          "playingxichange": ""
        },
        {
          "id": 12337,
          "overs": "0.4",
          "maidens": 0,
          "wickets": 1,
          "runs": 5,
          "economy": "7.5",
          "name": "Ramandeep Singh",
          "nickname": "Ramandeep Singh",
          "iscaptain": false,
          "iskeeper": false,
          "videotype": "",
          "videourl": "",
          "videoid": 0,
          "dots": 0,
          "balls": 4,
          "rpb": 1.25,
          "planid": 0,
          "imageid": 0,
          "premiumvideourl": "",
          "ispremiumfree": false,
          "inmatchchange": "",
          "isoverseas": false,
          "playingxichange": ""
        }
      ],
      "fow": {
        "fow": [
          {
            "batsmanid": 13866,
            "batsmanname": "Sai Sudharsan",
            "overnbr": 5.1,
            "runs": 57,
            "ballnbr": 31
          },
          {
            "batsmanid": 2258,
            "batsmanname": "Jos Buttler",
            "overnbr": 9.1,
            "runs": 95,
            "ballnbr": 55
          },
          {
            "batsmanid": 10945,
            "batsmanname": "Washington Sundar",
            "overnbr": 14.3,
            "runs": 141,
            "ballnbr": 87
          },
          {
            "batsmanid": 11808,
            "batsmanname": "Shubman Gill",
            "overnbr": 16.6,
            "runs": 158,
            "ballnbr": 102
          },
          {
            "batsmanid": 10693,
            "batsmanname": "Glenn Phillips",
            "overnbr": 19.1,
            "runs": 177,
            "ballnbr": 115
          }
        ]
      },
      "extras": {
        "legbyes": 2,
        "byes": 0,
        "wides": 4,
        "noballs": 0,
        "penalty": 0,
        "total": 6
      },
      "score": 181,
      "wickets": 5,
      "overs": 19.4,
      "runrate": 9.2,
      "batteamname": "Gujarat Titans",
      "batteamsname": "GT",
      "isdeclared": false,
      "isfollowon": false,
      "ballnbr": 118,
      "rpb": 1.53,
      "partnership": {
        "partnership": [
          {
            "id": 0,
            "bat1id": 13866,
            "bat1name": "Sai Sudharsan",
            "bat1runs": 22,
            "bat1fours": 1,
            "bat1sixes": 2,
            "bat2id": 11808,
            "bat2name": "Shubman Gill",
            "bat2runs": 34,
            "bat2fours": 4,
            "bat2sixes": 2,
            "totalruns": 57,
            "totalballs": 31,
            "bat1balls": 16,
            "bat2balls": 15,
            "teamname": "",
            "teamid": 0,
            "bat1ones": 3,
            "bat1twos": 0,
            "bat1threes": 1,
            "bat1fives": 0,
            "bat1boundaries": 1,
            "bat1sixers": 2,
            "bat2ones": 4,
            "bat2twos": 1,
            "bat2threes": 0,
            "bat2fives": 0,
            "bat2boundaries": 4,
            "bat2sixers": 2
          },
          {
            "id": 0,
            "bat1id": 2258,
            "bat1name": "Jos Buttler",
            "bat1runs": 25,
            "bat1fours": 2,
            "bat1sixes": 2,
            "bat2id": 11808,
            "bat2name": "Shubman Gill",
            "bat2runs": 13,
            "bat2fours": 2,
            "bat2sixes": 0,
            "totalruns": 38,
            "totalballs": 24,
            "bat1balls": 15,
            "bat2balls": 9,
            "teamname": "",
            "teamid": 0,
            "bat1ones": 5,
            "bat1twos": 0,
            "bat1threes": 0,
            "bat1fives": 0,
            "bat1boundaries": 2,
            "bat1sixers": 2,
            "bat2ones": 5,
            "bat2twos": 0,
            "bat2threes": 0,
            "bat2fives": 0,
            "bat2boundaries": 2,
            "bat2sixers": 0
          },
          {
            "id": 0,
            "bat1id": 10945,
            "bat1name": "Washington Sundar",
            "bat1runs": 13,
            "bat1fours": 1,
            "bat1sixes": 0,
            "bat2id": 11808,
            "bat2name": "Shubman Gill",
            "bat2runs": 31,
            "bat2fours": 1,
            "bat2sixes": 2,
            "totalruns": 46,
            "totalballs": 32,
            "bat1balls": 13,
            "bat2balls": 19,
            "teamname": "",
            "teamid": 0,
            "bat1ones": 7,
            "bat1twos": 1,
            "bat1threes": 0,
            "bat1fives": 0,
            "bat1boundaries": 1,
            "bat1sixers": 0,
            "bat2ones": 9,
            "bat2twos": 3,
            "bat2threes": 0,
            "bat2fives": 0,
            "bat2boundaries": 1,
            "bat2sixers": 2
          },
          {
            "id": 0,
            "bat1id": 10693,
            "bat1name": "Glenn Phillips",
            "bat1runs": 7,
            "bat1fours": 0,
            "bat1sixes": 0,
            "bat2id": 11808,
            "bat2name": "Shubman Gill",
            "bat2runs": 8,
            "bat2fours": 1,
            "bat2sixes": 0,
            "totalruns": 17,
            "totalballs": 15,
            "bat1balls": 8,
            "bat2balls": 7,
            "teamname": "",
            "teamid": 0,
            "bat1ones": 5,
            "bat1twos": 1,
            "bat1threes": 0,
            "bat1fives": 0,
            "bat1boundaries": 0,
            "bat1sixers": 0,
            "bat2ones": 4,
            "bat2twos": 0,
            "bat2threes": 0,
            "bat2fives": 0,
            "bat2boundaries": 1,
            "bat2sixers": 0
          },
          {
            "id": 0,
            "bat1id": 10693,
            "bat1name": "Glenn Phillips",
            "bat1runs": 12,
            "bat1fours": 2,
            "bat1sixes": 0,
            "bat2id": 9693,
            "bat2name": "Rahul Tewatia",
            "bat2runs": 6,
            "bat2fours": 0,
            "bat2sixes": 0,
            "totalruns": 19,
            "totalballs": 13,
            "bat1balls": 8,
            "bat2balls": 5,
            "teamname": "",
            "teamid": 0,
            "bat1ones": 4,
            "bat1twos": 0,
            "bat1threes": 0,
            "bat1fives": 0,
            "bat1boundaries": 2,
            "bat1sixers": 0,
            "bat2ones": 4,
            "bat2twos": 1,
            "bat2threes": 0,
            "bat2fives": 0,
            "bat2boundaries": 0,
            "bat2sixers": 0
          },
          {
            "id": 0,
            "bat1id": 10226,
            "bat1name": "Shahrukh Khan",
            "bat1runs": 3,
            "bat1fours": 0,
            "bat1sixes": 0,
            "bat2id": 9693,
            "bat2name": "Rahul Tewatia",
            "bat2runs": 1,
            "bat2fours": 0,
            "bat2sixes": 0,
            "totalruns": 4,
            "totalballs": 3,
            "bat1balls": 2,
            "bat2balls": 1,
            "teamname": "",
            "teamid": 0,
            "bat1ones": 1,
            "bat1twos": 1,
            "bat1threes": 0,
            "bat1fives": 0,
            "bat1boundaries": 0,
            "bat1sixers": 0,
            "bat2ones": 1,
            "bat2twos": 0,
            "bat2threes": 0,
            "bat2fives": 0,
            "bat2boundaries": 0,
            "bat2sixers": 0
          }
        ]
      }
    }
  ],
  "ismatchcomplete": true,
  "appindex": {
    "seotitle": "Cricket scorecard - GT vs KKR 25th Match,Indian Premier League 2026 | Cricbuzz.com",
    "weburl": "http://www.cricbuzz.com/live-cricket-scorecard/151796/gt-vs-kkr-25th-match-indian-premier-league-2026"
  },
  "status": "Gujarat Titans won by 5 wkts",
  "responselastupdated": 1776520234,
  "man_of_the_match": "Shubman Gill"
}